[{"no":"37","tag":["回復轉火"]},
{"no":"39","tag":["火轉回復"]},
{"no":"43","tag":["闇轉回復"]},
{"no":"45","tag":["回復轉闇"]},
{"no":"57","tag":["回復轉火"]},
{"no":"59","tag":["火轉回復"]},
{"no":"63","tag":["木轉火","邪魔轉火","回復轉木","毒轉木"]},
{"no":"65","tag":["火轉水","邪魔轉水","回復轉火","毒轉火"]},
{"no":"67","tag":["水轉木","邪魔轉木","回復轉水","毒轉水"]},
{"no":"90","tag":["火轉回復"]},
{"no":"91","tag":["火轉回復"]},
{"no":"98","tag":["水轉火"]},
{"no":"99","tag":["水轉火"]},
{"no":"100","tag":["木轉水"]},
{"no":"101","tag":["木轉水"]},
{"no":"102","tag":["火轉木"]},
{"no":"103","tag":["火轉木"]},
{"no":"104","tag":["闇轉光"]},
{"no":"105","tag":["闇轉光"]},
{"no":"106","tag":["回復轉火"]},
{"no":"107","tag":["回復轉火"]},
{"no":"108","tag":["光轉闇"]},
{"no":"109","tag":["光轉闇"]},
{"no":"110","tag":["回復轉闇"]},
{"no":"111","tag":["回復轉闇"]},
{"no":"154","tag":["光轉木","回復轉木","邪魔轉木","毒轉木"]},
{"no":"160","tag":["全轉火","全轉水","全轉木","全轉光","全轉暗","全轉回復"]},
{"no":"161","tag":["全轉火","全轉水","全轉回復"]},
{"no":"162","tag":["火轉水","木轉水"]},
{"no":"163","tag":["全轉火","全轉木","全轉回復"]},
{"no":"164","tag":["全轉火","全轉水","全轉木","全轉光","全轉闇"]},
{"no":"165","tag":["水轉闇","邪魔轉闇","毒轉闇"]},
{"no":"167","tag":["全轉水","全轉光","全轉回復"]},
{"no":"169","tag":["隨機轉光","隨機轉回復"]},
{"no":"173","tag":["邪魔轉木","毒轉木","隨機轉回復"]},
{"no":"175","tag":["隨機轉闇","隨機轉邪魔"]},
{"no":"177","tag":["火轉回復","光轉回復","毒轉回復"]},
{"no":"178","tag":["回復轉闇"]},
{"no":"180","tag":["木轉回復","闇轉回復","毒轉回復"]},
{"no":"181","tag":["回復轉光"]},
{"no":"183","tag":["回復轉水"]},
{"no":"184","tag":["回復轉木"]},
{"no":"185","tag":["回復轉光"]},
{"no":"202","tag":["火轉回復"]},
{"no":"211","tag":["闇轉火"]},
{"no":"212","tag":["光轉水"]},
{"no":"213","tag":["闇轉木"]},
{"no":"214","tag":["水轉光"]},
{"no":"215","tag":["水轉闇"]},
{"no":"221","tag":["回復轉水"]},
{"no":"222","tag":["回復轉水"]},
{"no":"223","tag":["回復轉木"]},
{"no":"224","tag":["回復轉木"]},
{"no":"225","tag":["回復轉光"]},
{"no":"226","tag":["回復轉光"]},
{"no":"229","tag":["水轉火"]},
{"no":"230","tag":["木轉水"]},
{"no":"231","tag":["火轉木"]},
{"no":"232","tag":["闇轉光"]},
{"no":"233","tag":["光轉闇"]},
{"no":"234","tag":["隨機轉光"]},
{"no":"240","tag":["水轉回復"]},
{"no":"241","tag":["水轉回復"]},
{"no":"251","tag":["隨機轉闇"]},
{"no":"253","tag":["木轉回復","光轉回復","毒轉回復"]},
{"no":"254","tag":["回復轉火"]},
{"no":"256","tag":["火轉回復","闇轉回復","毒轉回復"]},
{"no":"257","tag":["回復轉水"]},
{"no":"259","tag":["水轉回復","光轉回復","毒轉回復"]},
{"no":"260","tag":["回復轉木"]},
{"no":"261","tag":["光轉闇","回復轉闇"]},
{"no":"288","tag":["木轉回復"]},
{"no":"289","tag":["木轉回復"]},
{"no":"290","tag":["木轉回復"]},
{"no":"291","tag":["火轉回復"]},
{"no":"292","tag":["火轉回復"]},
{"no":"293","tag":["火轉回復"]},
{"no":"294","tag":["水轉回復"]},
{"no":"295","tag":["水轉回復"]},
{"no":"296","tag":["水轉回復"]},
{"no":"297","tag":["闇轉回復"]},
{"no":"298","tag":["闇轉回復"]},
{"no":"299","tag":["闇轉回復"]},
{"no":"300","tag":["光轉回復"]},
{"no":"301","tag":["光轉回復"]},
{"no":"302","tag":["光轉回復"]},
{"no":"304","tag":["木轉回復"]},
{"no":"306","tag":["火轉回復"]},
{"no":"308","tag":["水轉回復"]},
{"no":"309","tag":["闇轉光","回復轉光"]},
{"no":"343","tag":["木轉回復"]},
{"no":"347","tag":["水轉回復"]},
{"no":"378","tag":["木轉火","邪魔轉火","回復轉木","毒轉木"]},
{"no":"379","tag":["木轉火","邪魔轉火","回復轉木","毒轉木"]},
{"no":"380","tag":["火轉水","邪魔轉水","回復轉火","毒轉火"]},
{"no":"381","tag":["火轉水","邪魔轉水","回復轉火","毒轉火"]},
{"no":"382","tag":["水轉木","邪魔轉木","回復轉水","毒轉水"]},
{"no":"383","tag":["水轉木","邪魔轉木","回復轉水","毒轉水"]},
{"no":"384","tag":["闇轉光","邪魔轉光","回復轉闇","毒轉闇"]},
{"no":"385","tag":["闇轉光","邪魔轉光","回復轉闇","毒轉闇"]},
{"no":"386","tag":["光轉闇","邪魔轉闇","回復轉光","毒轉光"]},
{"no":"387","tag":["光轉闇","邪魔轉闇","回復轉光","毒轉光"]},
{"no":"414","tag":["木轉回復","光轉回復","毒轉回復"]},
{"no":"415","tag":["木轉回復","光轉回復","毒轉回復"]},
{"no":"416","tag":["木轉回復","光轉回復","毒轉回復"]},
{"no":"417","tag":["火轉回復","闇轉回復","毒轉回復"]},
{"no":"418","tag":["火轉回復","闇轉回復","毒轉回復"]},
{"no":"419","tag":["火轉回復","闇轉回復","毒轉回復"]},
{"no":"420","tag":["水轉回復","光轉回復","毒轉回復"]},
{"no":"421","tag":["水轉回復","光轉回復","毒轉回復"]},
{"no":"422","tag":["水轉回復","光轉回復","毒轉回復"]},
{"no":"423","tag":["木轉回復","闇轉回復","毒轉回復"]},
{"no":"424","tag":["木轉回復","闇轉回復","毒轉回復"]},
{"no":"425","tag":["木轉回復","闇轉回復","毒轉回復"]},
{"no":"426","tag":["火轉回復","光轉回復","毒轉回復"]},
{"no":"427","tag":["火轉回復","光轉回復","毒轉回復"]},
{"no":"428","tag":["火轉回復","光轉回復","毒轉回復"]},
{"no":"429","tag":["全轉火","全轉水","全轉木","全轉光","全轉暗","全轉回復"]},
{"no":"449","tag":["隨機轉火"]},
{"no":"450","tag":["隨機轉火"]},
{"no":"469","tag":["隨機轉火"]},
{"no":"473","tag":["全轉木","全轉光","全轉闇","全轉回復"]},
{"no":"486","tag":["隨機轉闇"]},
{"no":"487","tag":["隨機轉闇"]},
{"no":"498","tag":["木轉闇"]},
{"no":"499","tag":["木轉闇"]},
{"no":"512","tag":["回復轉火"]},
{"no":"513","tag":["回復轉水"]},
{"no":"514","tag":["回復轉木"]},
{"no":"515","tag":["回復轉光"]},
{"no":"516","tag":["回復轉闇"]},
{"no":"526","tag":["隨機轉火"]},
{"no":"527","tag":["隨機轉火"]},
{"no":"532","tag":["隨機轉火"]},
{"no":"533","tag":["隨機轉火"]},
{"no":"555","tag":["光轉火"]},
{"no":"556","tag":["光轉火"]},
{"no":"557","tag":["闇轉水"]},
{"no":"558","tag":["闇轉水"]},
{"no":"559","tag":["水轉木"]},
{"no":"560","tag":["水轉木"]},
{"no":"561","tag":["木轉光"]},
{"no":"562","tag":["木轉光"]},
{"no":"563","tag":["火轉闇"]},
{"no":"564","tag":["火轉闇"]},
{"no":"565","tag":["全轉火"]},
{"no":"566","tag":["全轉火"]},
{"no":"567","tag":["水轉火","回復轉火"]},
{"no":"568","tag":["水轉火","回復轉火"]},
{"no":"569","tag":["木轉水","回復轉水"]},
{"no":"570","tag":["木轉水","回復轉水"]},
{"no":"571","tag":["火轉木","回復轉木"]},
{"no":"572","tag":["火轉木","回復轉木"]},
{"no":"573","tag":["闇轉光","回復轉光"]},
{"no":"574","tag":["闇轉光","回復轉光"]},
{"no":"575","tag":["光轉闇","回復轉闇"]},
{"no":"576","tag":["光轉闇","回復轉闇"]},
{"no":"601","tag":["闇轉回復"]},
{"no":"603","tag":["光轉回復"]},
{"no":"617","tag":["水轉火","回復轉火"]},
{"no":"618","tag":["木轉水","回復轉水"]},
{"no":"619","tag":["火轉木","回復轉木"]},
{"no":"620","tag":["光轉火","闇轉回復"]},
{"no":"621","tag":["光轉火","闇轉回復"]},
{"no":"622","tag":["光轉水","闇轉回復"]},
{"no":"623","tag":["光轉水","闇轉回復"]},
{"no":"624","tag":["光轉木","闇轉回復"]},
{"no":"625","tag":["光轉木","闇轉回復"]},
{"no":"626","tag":["全轉回復"]},
{"no":"627","tag":["全轉回復"]},
{"no":"628","tag":["隨機轉回復"]},
{"no":"629","tag":["隨機轉回復"]},
{"no":"630","tag":["木轉火"]},
{"no":"631","tag":["木轉火"]},
{"no":"632","tag":["火轉水"]},
{"no":"633","tag":["火轉水"]},
{"no":"634","tag":["火轉木"]},
{"no":"635","tag":["火轉木"]},
{"no":"636","tag":["水轉光"]},
{"no":"637","tag":["水轉光"]},
{"no":"646","tag":["隨機轉闇"]},
{"no":"647","tag":["隨機轉闇"]},
{"no":"650","tag":["全轉木"]},
{"no":"651","tag":["全轉木"]},
{"no":"663","tag":["木轉闇"]},
{"no":"665","tag":["火轉水"]},
{"no":"671","tag":["光轉木","回復轉光"]},
{"no":"672","tag":["光轉木","回復轉光"]},
{"no":"674","tag":["水轉光"]},
{"no":"676","tag":["光轉回復"]},
{"no":"678","tag":["火轉木"]},
{"no":"679","tag":["闇轉光","邪魔轉光","回復轉闇","毒轉闇"]},
{"no":"689","tag":["回復轉火"]},
{"no":"690","tag":["火轉回復"]},
{"no":"692","tag":["回復轉水"]},
{"no":"693","tag":["回復轉木"]},
{"no":"694","tag":["回復轉光"]},
{"no":"697","tag":["木轉水","回復轉闇"]},
{"no":"698","tag":["木轉水","回復轉闇"]},
{"no":"716","tag":["光轉木","回復轉光"]},
{"no":"717","tag":["闇轉水"]},
{"no":"718","tag":["火轉闇"]},
{"no":"727","tag":["闇轉回復"]},
{"no":"745","tag":["全轉火","全轉木","全轉光"]},
{"no":"746","tag":["全轉火","全轉木","全轉光"]},
{"no":"747","tag":["全轉水","全轉木","全轉闇"]},
{"no":"748","tag":["全轉水","全轉木","全轉闇"]},
{"no":"749","tag":["全轉木","全轉光","全轉闇"]},
{"no":"750","tag":["全轉木","全轉光","全轉闇"]},
{"no":"753","tag":["全轉火","全轉水","全轉闇"]},
{"no":"754","tag":["全轉火","全轉水","全轉闇"]},
{"no":"757","tag":["木轉回復"]},
{"no":"758","tag":["火轉回復"]},
{"no":"759","tag":["水轉回復"]},
{"no":"760","tag":["闇轉回復"]},
{"no":"761","tag":["光轉回復"]},
{"no":"763","tag":["水轉火","回復轉火"]},
{"no":"767","tag":["火轉木","回復轉木"]},
{"no":"779","tag":["水轉木"]},
{"no":"788","tag":["光轉火","闇轉回復"]},
{"no":"790","tag":["光轉水","闇轉回復"]},
{"no":"792","tag":["光轉木","闇轉回復"]},
{"no":"794","tag":["闇轉光","回復轉光"]},
{"no":"796","tag":["光轉闇","回復轉闇"]},
{"no":"801","tag":["火轉水","回復轉木"]},
{"no":"802","tag":["火轉水","回復轉木"]},
{"no":"822","tag":["水轉火"]},
{"no":"823","tag":["木轉水"]},
{"no":"824","tag":["火轉木"]},
{"no":"825","tag":["闇轉光"]},
{"no":"826","tag":["光轉闇"]},
{"no":"834","tag":["闇轉水","木轉回復"]},
{"no":"835","tag":["闇轉水","木轉回復"]},
{"no":"840","tag":["火轉木","闇轉回復"]},
{"no":"841","tag":["火轉木","闇轉回復"]},
{"no":"845","tag":["木轉水","回復轉水"]},
{"no":"853","tag":["木轉火"]},
{"no":"883","tag":["光轉木","回復轉光"]},
{"no":"889","tag":["水轉火","回復轉火"]},
{"no":"890","tag":["木轉水","回復轉水"]},
{"no":"891","tag":["火轉木","回復轉木"]},
{"no":"892","tag":["闇轉光","回復轉光"]},
{"no":"893","tag":["光轉闇","回復轉闇"]},
{"no":"894","tag":["回復轉闇"]},
{"no":"895","tag":["回復轉闇"]},
{"no":"896","tag":["全轉火","全轉木","全轉光"]},
{"no":"897","tag":["全轉火","全轉木","全轉光"]},
{"no":"898","tag":["全轉水","全轉木","全轉闇"]},
{"no":"899","tag":["全轉水","全轉木","全轉闇"]},
{"no":"900","tag":["全轉木","全轉光","全轉闇"]},
{"no":"901","tag":["全轉木","全轉光","全轉闇"]},
{"no":"904","tag":["全轉火","全轉水","全轉闇"]},
{"no":"905","tag":["全轉火","全轉水","全轉闇"]},
{"no":"911","tag":["全轉火","全轉闇"]},
{"no":"912","tag":["全轉火","全轉闇"]},
{"no":"913","tag":["全轉木","全轉闇"]},
{"no":"914","tag":["全轉木","全轉闇"]},
{"no":"915","tag":["全轉光","全轉回復"]},
{"no":"916","tag":["隨機轉闇","隨機轉回復"]},
{"no":"926","tag":["隨機轉火"]},
{"no":"927","tag":["隨機轉火"]},
{"no":"932","tag":["邪魔轉闇"]},
{"no":"933","tag":["邪魔轉闇"]},
{"no":"937","tag":["木轉火","邪魔轉火","回復轉木","毒轉木"]},
{"no":"939","tag":["火轉水","邪魔轉水","回復轉火","毒轉火"]},
{"no":"941","tag":["水轉木","邪魔轉木","回復轉水","毒轉水"]},
{"no":"943","tag":["闇轉光","邪魔轉光","回復轉闇","毒轉闇"]},
{"no":"945","tag":["光轉闇","邪魔轉闇","回復轉光","毒轉光"]},
{"no":"953","tag":["水轉回復","光轉回復","毒轉回復"]},
{"no":"955","tag":["回復轉光"]},
{"no":"959","tag":["火轉回復","光轉回復","毒轉回復"]},
{"no":"963","tag":["闇轉火"]},
{"no":"964","tag":["闇轉火"]},
{"no":"966","tag":["光轉水"]},
{"no":"967","tag":["光轉水"]},
{"no":"969","tag":["闇轉木"]},
{"no":"970","tag":["闇轉木"]},
{"no":"972","tag":["回復轉水"]},
{"no":"973","tag":["回復轉水"]},
{"no":"979","tag":["光轉火"]},
{"no":"980","tag":["火轉水","回復轉木"]},
{"no":"982","tag":["回復轉闇"]},
{"no":"983","tag":["回復轉闇"]},
{"no":"984","tag":["回復轉火"]},
{"no":"991","tag":["木轉毒"]},
{"no":"1000","tag":["木轉闇"]},
{"no":"1001","tag":["木轉闇"]},
{"no":"1007","tag":["木轉光"]},
{"no":"1036","tag":["水轉火","回復轉火"]},
{"no":"1038","tag":["火轉木","回復轉木"]},
{"no":"1040","tag":["火轉水"]},
{"no":"1042","tag":["火轉回復","闇轉回復","毒轉回復"]},
{"no":"1044","tag":["木轉回復","闇轉回復","毒轉回復"]},
{"no":"1046","tag":["光轉闇","回復轉闇"]},
{"no":"1052","tag":["木轉水","回復轉水"]},
{"no":"1065","tag":["木轉火","闇轉回復"]},
{"no":"1066","tag":["木轉火","闇轉回復"]},
{"no":"1067","tag":["火轉水","光轉回復"]},
{"no":"1068","tag":["火轉水","光轉回復"]},
{"no":"1069","tag":["水轉木","火轉回復"]},
{"no":"1070","tag":["水轉木","火轉回復"]},
{"no":"1071","tag":["水轉光","闇轉回復"]},
{"no":"1072","tag":["水轉光","闇轉回復"]},
{"no":"1073","tag":["木轉闇","光轉回復"]},
{"no":"1074","tag":["木轉闇","光轉回復"]},
{"no":"1075","tag":["木轉回復"]},
{"no":"1076","tag":["木轉回復"]},
{"no":"1077","tag":["火轉回復"]},
{"no":"1078","tag":["火轉回復"]},
{"no":"1079","tag":["水轉回復"]},
{"no":"1080","tag":["水轉回復"]},
{"no":"1081","tag":["闇轉回復"]},
{"no":"1082","tag":["闇轉回復"]},
{"no":"1083","tag":["光轉回復"]},
{"no":"1084","tag":["光轉回復"]},
{"no":"1085","tag":["隨機轉火","隨機轉回復"]},
{"no":"1086","tag":["全轉水","全轉木","全轉回復"]},
{"no":"1088","tag":["全轉水","全轉闇"]},
{"no":"1089","tag":["全轉水","全轉闇"]},
{"no":"1090","tag":["闇轉火"]},
{"no":"1091","tag":["光轉水"]},
{"no":"1092","tag":["闇轉木"]},
{"no":"1093","tag":["水轉光"]},
{"no":"1094","tag":["水轉闇"]},
{"no":"1100","tag":["火轉回復"]},
{"no":"1116","tag":["水轉回復"]},
{"no":"1117","tag":["水轉回復"]},
{"no":"1120","tag":["木轉火","回復轉火"]},
{"no":"1121","tag":["木轉火","回復轉火"]},
{"no":"1128","tag":["回復轉毒"]},
{"no":"1129","tag":["回復轉毒"]},
{"no":"1130","tag":["全轉木","全轉光"]},
{"no":"1131","tag":["全轉木","全轉光"]},
{"no":"1137","tag":["木轉回復"]},
{"no":"1139","tag":["火轉回復"]},
{"no":"1141","tag":["水轉回復"]},
{"no":"1143","tag":["闇轉回復"]},
{"no":"1145","tag":["光轉回復"]},
{"no":"1160","tag":["火轉回復","水轉回復"]},
{"no":"1161","tag":["火轉回復","水轉回復"]},
{"no":"1176","tag":["全轉火","全轉光"]},
{"no":"1178","tag":["木轉火","闇轉回復"]},
{"no":"1179","tag":["木轉火","闇轉回復"]},
{"no":"1180","tag":["火轉水","光轉回復"]},
{"no":"1181","tag":["火轉水","光轉回復"]},
{"no":"1182","tag":["水轉木","火轉回復"]},
{"no":"1183","tag":["水轉木","火轉回復"]},
{"no":"1184","tag":["水轉光","闇轉回復"]},
{"no":"1185","tag":["水轉光","闇轉回復"]},
{"no":"1186","tag":["木轉闇","光轉回復"]},
{"no":"1187","tag":["木轉闇","光轉回復"]},
{"no":"1188","tag":["全轉木"]},
{"no":"1189","tag":["全轉木"]},
{"no":"1191","tag":["光轉火"]},
{"no":"1192","tag":["闇轉水"]},
{"no":"1193","tag":["水轉木"]},
{"no":"1194","tag":["木轉光"]},
{"no":"1195","tag":["火轉闇"]},
{"no":"1202","tag":["闇轉火","回復轉火"]},
{"no":"1203","tag":["闇轉火","回復轉火"]},
{"no":"1208","tag":["回復轉水"]},
{"no":"1209","tag":["回復轉木"]},
{"no":"1216","tag":["隨機轉回復"]},
{"no":"1219","tag":["隨機轉光"]},
{"no":"1220","tag":["隨機轉光"]},
{"no":"1231","tag":["水轉火"]},
{"no":"1232","tag":["水轉火"]},
{"no":"1235","tag":["闇轉木","回復轉木"]},
{"no":"1236","tag":["闇轉木","回復轉木"]},
{"no":"1237","tag":["闇轉光","火轉回復"]},
{"no":"1238","tag":["闇轉光","火轉回復"]},
{"no":"1241","tag":["毒轉木","回復轉木"]},
{"no":"1242","tag":["毒轉木","回復轉木"]},
{"no":"1243","tag":["毒轉火","回復轉火"]},
{"no":"1244","tag":["毒轉火","回復轉火"]},
{"no":"1253","tag":["光轉火","闇轉回復"]},
{"no":"1254","tag":["光轉水","闇轉回復"]},
{"no":"1255","tag":["光轉木","闇轉回復"]},
{"no":"1256","tag":["全轉回復"]},
{"no":"1257","tag":["木轉火"]},
{"no":"1258","tag":["火轉水"]},
{"no":"1259","tag":["火轉木"]},
{"no":"1260","tag":["火轉木"]},
{"no":"1261","tag":["水轉光"]},
{"no":"1262","tag":["全轉火","全轉木","全轉光"]},
{"no":"1263","tag":["全轉火","全轉木","全轉光"]},
{"no":"1264","tag":["全轉水","全轉木","全轉闇"]},
{"no":"1265","tag":["全轉水","全轉木","全轉闇"]},
{"no":"1266","tag":["全轉木","全轉光","全轉闇"]},
{"no":"1267","tag":["全轉木","全轉光","全轉闇"]},
{"no":"1268","tag":["全轉火","全轉水","全轉闇"]},
{"no":"1269","tag":["全轉火","全轉水","全轉闇"]},
{"no":"1270","tag":["回復轉火"]},
{"no":"1271","tag":["回復轉火"]},
{"no":"1278","tag":["闇轉水","回復轉水"]},
{"no":"1279","tag":["闇轉水","回復轉水"]},
{"no":"1282","tag":["回復轉火"]},
{"no":"1283","tag":["回復轉火"]},
{"no":"1284","tag":["火轉回復"]},
{"no":"1285","tag":["火轉回復"]},
{"no":"1286","tag":["火轉木","回復轉木"]},
{"no":"1287","tag":["火轉木","回復轉木"]},
{"no":"1288","tag":["回復轉光"]},
{"no":"1289","tag":["回復轉光"]},
{"no":"1290","tag":["水轉闇"]},
{"no":"1291","tag":["水轉闇"]},
{"no":"1294","tag":["光轉水","回復轉水","邪魔轉水","毒轉水"]},
{"no":"1295","tag":["全轉火","全轉水","全轉木","全轉光","全轉暗","全轉回復"]},
{"no":"1297","tag":["火轉水","回復轉木"]},
{"no":"1301","tag":["木轉火","邪魔轉火","回復轉木","毒轉木"]},
{"no":"1302","tag":["火轉水","邪魔轉水","回復轉火","毒轉火"]},
{"no":"1303","tag":["水轉木","邪魔轉木","回復轉水","毒轉水"]},
{"no":"1304","tag":["闇轉光","邪魔轉光","回復轉闇","毒轉闇"]},
{"no":"1305","tag":["光轉闇","邪魔轉闇","回復轉光","毒轉光"]},
{"no":"1309","tag":["木轉回復","光轉回復","毒轉回復"]},
{"no":"1314","tag":["水轉光"]},
{"no":"1316","tag":["水轉闇"]},
{"no":"1324","tag":["木轉闇","回復轉闇","邪魔轉闇","毒轉闇"]},
{"no":"1325","tag":["全轉火","全轉木","全轉光"]},
{"no":"1326","tag":["全轉水","全轉木","全轉闇"]},
{"no":"1327","tag":["全轉木","全轉光","全轉闇"]},
{"no":"1329","tag":["全轉火","全轉水","全轉闇"]},
{"no":"1330","tag":["隨機轉火"]},
{"no":"1331","tag":["隨機轉火"]},
{"no":"1332","tag":["隨機轉水"]},
{"no":"1333","tag":["隨機轉水"]},
{"no":"1334","tag":["隨機轉木"]},
{"no":"1335","tag":["隨機轉木"]},
{"no":"1359","tag":["全轉光","全轉闇","全轉回復"]},
{"no":"1360","tag":["全轉光","全轉闇","全轉回復"]},
{"no":"1366","tag":["水轉火"]},
{"no":"1368","tag":["闇轉木","回復轉木"]},
{"no":"1369","tag":["闇轉光","火轉回復"]},
{"no":"1391","tag":["毒轉回復"]},
{"no":"1398","tag":["火轉闇","邪魔轉闇","毒轉闇"]},
{"no":"1399","tag":["火轉闇","邪魔轉闇","毒轉闇"]},
{"no":"1400","tag":["木轉水","毒轉水"]},
{"no":"1401","tag":["木轉水","毒轉水"]},
{"no":"1412","tag":["水轉回復"]},
{"no":"1413","tag":["水轉回復"]},
{"no":"1414","tag":["木轉回復"]},
{"no":"1415","tag":["木轉回復"]},
{"no":"1416","tag":["火轉回復"]},
{"no":"1417","tag":["火轉回復"]},
{"no":"1418","tag":["水轉回復"]},
{"no":"1419","tag":["水轉回復"]},
{"no":"1420","tag":["木轉回復"]},
{"no":"1421","tag":["木轉回復"]},
{"no":"1424","tag":["闇轉木"]},
{"no":"1425","tag":["闇轉木"]},
{"no":"1436","tag":["回復轉光","闇轉回復"]},
{"no":"1437","tag":["回復轉光","闇轉回復"]},
{"no":"1438","tag":["回復轉光","邪魔轉光"]},
{"no":"1439","tag":["回復轉光","邪魔轉光"]},
{"no":"1441","tag":["木轉火","回復轉火"]},
{"no":"1451","tag":["木轉火"]},
{"no":"1453","tag":["火轉木"]},
{"no":"1455","tag":["木轉水","回復轉水"]},
{"no":"1460","tag":["全轉水"]},
{"no":"1461","tag":["全轉水"]},
{"no":"1462","tag":["水轉回復"]},
{"no":"1463","tag":["水轉回復"]},
{"no":"1475","tag":["木轉回復","闇轉回復","毒轉回復"]},
{"no":"1478","tag":["水轉回復","光轉回復","毒轉回復"]},
{"no":"1479","tag":["邪魔轉闇"]},
{"no":"1480","tag":["邪魔轉闇"]},
{"no":"1482","tag":["水轉回復"]},
{"no":"1484","tag":["水轉回復"]},
{"no":"1486","tag":["木轉回復"]},
{"no":"1491","tag":["邪魔轉回復","毒轉回復"]},
{"no":"1492","tag":["邪魔轉回復","毒轉回復"]},
{"no":"1497","tag":["回復轉木","邪魔轉木"]},
{"no":"1498","tag":["回復轉木","邪魔轉木"]},
{"no":"1499","tag":["全轉水","全轉木","全轉回復"]},
{"no":"1500","tag":["全轉水","全轉木","全轉回復"]},
{"no":"1501","tag":["回復轉光"]},
{"no":"1502","tag":["回復轉火"]},
{"no":"1503","tag":["回復轉火"]},
{"no":"1504","tag":["回復轉水"]},
{"no":"1505","tag":["回復轉水"]},
{"no":"1506","tag":["回復轉光"]},
{"no":"1507","tag":["回復轉光"]},
{"no":"1511","tag":["木轉回復","光轉回復","毒轉回復"]},
{"no":"1512","tag":["火轉回復","闇轉回復","毒轉回復"]},
{"no":"1513","tag":["水轉回復","光轉回復","毒轉回復"]},
{"no":"1514","tag":["木轉回復","闇轉回復","毒轉回復"]},
{"no":"1515","tag":["火轉回復","光轉回復","毒轉回復"]},
{"no":"1516","tag":["回復轉木"]},
{"no":"1517","tag":["回復轉木"]},
{"no":"1521","tag":["毒轉木","回復轉木"]},
{"no":"1526","tag":["水轉回復"]},
{"no":"1527","tag":["木轉回復"]},
{"no":"1528","tag":["火轉回復"]},
{"no":"1529","tag":["水轉光"]},
{"no":"1530","tag":["隨機轉回復"]},
{"no":"1531","tag":["全轉水"]},
{"no":"1532","tag":["全轉水"]},
{"no":"1533","tag":["闇轉火"]},
{"no":"1537","tag":["木轉回復"]},
{"no":"1538","tag":["木轉回復"]},
{"no":"1539","tag":["火轉回復"]},
{"no":"1540","tag":["火轉回復"]},
{"no":"1541","tag":["水轉回復"]},
{"no":"1542","tag":["水轉回復"]},
{"no":"1543","tag":["闇轉回復"]},
{"no":"1544","tag":["闇轉回復"]},
{"no":"1545","tag":["光轉回復"]},
{"no":"1546","tag":["光轉回復"]},
{"no":"1560","tag":["火轉闇","邪魔轉闇","毒轉闇"]},
{"no":"1561","tag":["木轉水","毒轉水"]},
{"no":"1562","tag":["回復轉木","邪魔轉木"]},
{"no":"1567","tag":["全轉水","全轉木","全轉光"]},
{"no":"1568","tag":["全轉水","全轉木","全轉光"]},
{"no":"1580","tag":["縦轉回復"]},
{"no":"1581","tag":["縦轉回復"]},
{"no":"1582","tag":["縦轉回復"]},
{"no":"1585","tag":["全轉火","全轉水","全轉木","全轉光","全轉闇"]},
{"no":"1586","tag":["全轉火","全轉水","全轉木","全轉光","全轉闇"]},
{"no":"1587","tag":["全轉火","全轉水","全轉木","全轉光","全轉暗","全轉回復"]},
{"no":"1588","tag":["全轉火","全轉水","全轉木","全轉光","全轉暗","全轉回復"]},
{"no":"1591","tag":["隨機轉火"]},
{"no":"1592","tag":["隨機轉水"]},
{"no":"1593","tag":["隨機轉木"]},
{"no":"1594","tag":["縦轉光"]},
{"no":"1595","tag":["水轉闇"]},
{"no":"1596","tag":["毒轉火","回復轉火"]},
{"no":"1598","tag":["横轉木"]},
{"no":"1602","tag":["光轉水","回復轉木"]},
{"no":"1609","tag":["全轉火","全轉水","全轉光","全轉回復"]},
{"no":"1610","tag":["全轉火","全轉水","全轉光","全轉回復"]},
{"no":"1611","tag":["全轉火","全轉木"]},
{"no":"1612","tag":["全轉火","全轉木"]},
{"no":"1614","tag":["横轉火"]},
{"no":"1615","tag":["横轉火"]},
{"no":"1616","tag":["横轉水"]},
{"no":"1617","tag":["横轉水"]},
{"no":"1618","tag":["横轉木"]},
{"no":"1619","tag":["横轉木"]},
{"no":"1620","tag":["縦轉光"]},
{"no":"1621","tag":["縦轉光"]},
{"no":"1622","tag":["縦轉闇"]},
{"no":"1623","tag":["縦轉闇"]},
{"no":"1624","tag":["横轉回復"]},
{"no":"1625","tag":["横轉回復"]},
{"no":"1626","tag":["邪魔轉回復","毒轉回復"]},
{"no":"1627","tag":["邪魔轉回復","毒轉回復"]},
{"no":"1628","tag":["全轉火","全轉木","全轉闇"]},
{"no":"1629","tag":["全轉火","全轉木","全轉闇"]},
{"no":"1630","tag":["回復轉光","邪魔轉光"]},
{"no":"1631","tag":["回復轉光","邪魔轉光"]},
{"no":"1633","tag":["木轉火","邪魔轉火","回復轉木","毒轉木"]},
{"no":"1635","tag":["火轉回復","闇轉回復","毒轉回復"]},
{"no":"1637","tag":["水轉回復"]},
{"no":"1639","tag":["木轉回復","闇轉回復","毒轉回復"]},
{"no":"1641","tag":["光轉闇","邪魔轉闇","回復轉光","毒轉光"]},
{"no":"1645","tag":["全轉火","全轉闇"]},
{"no":"1646","tag":["隨機轉闇"]},
{"no":"1647","tag":["回復轉闇"]},
{"no":"1648","tag":["回復轉闇"]},
{"no":"1659","tag":["回復轉火"]},
{"no":"1660","tag":["回復轉火"]},
{"no":"1661","tag":["縦轉水"]},
{"no":"1662","tag":["縦轉水"]},
{"no":"1663","tag":["縦轉木"]},
{"no":"1664","tag":["縦轉木"]},
{"no":"1669","tag":["全轉火","全轉水","全轉回復"]},
{"no":"1670","tag":["全轉火","全轉水","全轉回復"]},
{"no":"1671","tag":["全轉火","全轉木","全轉回復"]},
{"no":"1672","tag":["全轉火","全轉木","全轉回復"]},
{"no":"1673","tag":["全轉水","全轉木","全轉回復"]},
{"no":"1674","tag":["全轉水","全轉木","全轉回復"]},
{"no":"1675","tag":["全轉火","全轉水","全轉光"]},
{"no":"1676","tag":["全轉火","全轉水","全轉光"]},
{"no":"1677","tag":["縦轉光","縦轉水"]},
{"no":"1678","tag":["縦轉光","縦轉水"]},
{"no":"1690","tag":["火轉水","邪魔轉水","回復轉火","毒轉火"]},
{"no":"1692","tag":["横轉水"]},
{"no":"1694","tag":["縦轉闇"]},
{"no":"1696","tag":["邪魔轉回復","毒轉回復"]},
{"no":"1704","tag":["横轉回復"]},
{"no":"1705","tag":["横轉回復"]},
{"no":"1706","tag":["邪魔轉回復","毒轉回復"]},
{"no":"1707","tag":["邪魔轉回復","毒轉回復"]},
{"no":"1716","tag":["毒轉木","回復轉木"]},
{"no":"1717","tag":["毒轉木","回復轉木"]},
{"no":"1718","tag":["全轉水","全轉木","全轉光","全轉回復"]},
{"no":"1719","tag":["全轉水","全轉木","全轉光","全轉回復"]},
{"no":"1720","tag":["闇轉光","邪魔轉光"]},
{"no":"1721","tag":["闇轉光","邪魔轉光"]},
{"no":"1722","tag":["縦轉木","縦轉光"]},
{"no":"1723","tag":["縦轉木","縦轉光"]},
{"no":"1725","tag":["回復轉光","邪魔轉光"]},
{"no":"1726","tag":["水轉火","回復轉闇"]},
{"no":"1727","tag":["回復轉光"]},
{"no":"1728","tag":["回復轉火"]},
{"no":"1729","tag":["回復轉水"]},
{"no":"1730","tag":["回復轉木"]},
{"no":"1731","tag":["回復轉闇"]},
{"no":"1732","tag":["木轉火","闇轉回復"]},
{"no":"1733","tag":["火轉水","光轉回復"]},
{"no":"1734","tag":["水轉木","火轉回復"]},
{"no":"1735","tag":["水轉光","闇轉回復"]},
{"no":"1736","tag":["木轉闇","光轉回復"]},
{"no":"1738","tag":["水轉火"]},
{"no":"1739","tag":["水轉火"]},
{"no":"1742","tag":["闇轉木","回復轉木"]},
{"no":"1743","tag":["闇轉木","回復轉木"]},
{"no":"1744","tag":["闇轉光","火轉回復"]},
{"no":"1745","tag":["闇轉光","火轉回復"]},
{"no":"1747","tag":["全轉火","全轉水","全轉木","全轉光","全轉闇"]},
{"no":"1749","tag":["隨機轉火"]},
{"no":"1750","tag":["隨機轉火"]},
{"no":"1751","tag":["隨機轉水"]},
{"no":"1752","tag":["隨機轉水"]},
{"no":"1753","tag":["隨機轉木"]},
{"no":"1754","tag":["隨機轉木"]},
{"no":"1755","tag":["隨機轉光"]},
{"no":"1756","tag":["隨機轉光"]},
{"no":"1757","tag":["隨機轉闇"]},
{"no":"1758","tag":["隨機轉闇"]},
{"no":"1762","tag":["全轉水"]},
{"no":"1763","tag":["全轉木"]},
{"no":"1785","tag":["回復轉光"]},
{"no":"1786","tag":["全轉火","全轉木","全轉光"]},
{"no":"1787","tag":["全轉水","全轉木","全轉闇"]},
{"no":"1788","tag":["全轉木","全轉光","全轉闇"]},
{"no":"1790","tag":["全轉火","全轉水","全轉闇"]},
{"no":"1793","tag":["全轉火","全轉闇"]},
{"no":"1794","tag":["隨機轉回復"]},
{"no":"1797","tag":["全轉火","全轉木","全轉闇"]},
{"no":"1798","tag":["全轉火","全轉木","全轉闇"]},
{"no":"1799","tag":["隨機轉火","隨機轉木"]},
{"no":"1800","tag":["隨機轉火","隨機轉木"]},
{"no":"1801","tag":["隨機轉火","隨機轉水"]},
{"no":"1802","tag":["隨機轉火","隨機轉水"]},
{"no":"1804","tag":["隨機轉光"]},
{"no":"1808","tag":["木轉水","毒轉水"]},
{"no":"1809","tag":["隨機轉火","隨機轉水"]},
{"no":"1810","tag":["火轉闇","邪魔轉闇","毒轉闇"]},
{"no":"1811","tag":["水轉火"]},
{"no":"1812","tag":["水轉火"]},
{"no":"1815","tag":["闇轉木","回復轉木"]},
{"no":"1816","tag":["闇轉木","回復轉木"]},
{"no":"1817","tag":["闇轉光","火轉回復"]},
{"no":"1818","tag":["闇轉光","火轉回復"]},
{"no":"1821","tag":["毒轉火","回復轉火"]},
{"no":"1822","tag":["毒轉火","回復轉火"]},
{"no":"1826","tag":["光轉回復"]},
{"no":"1827","tag":["光轉回復"]},
{"no":"1828","tag":["全轉水","全轉木","全轉光","全轉闇"]},
{"no":"1829","tag":["全轉水","全轉木","全轉光","全轉闇"]},
{"no":"1830","tag":["隨機轉木","隨機轉闇"]},
{"no":"1831","tag":["隨機轉木","隨機轉闇"]},
{"no":"1832","tag":["隨機轉光"]},
{"no":"1833","tag":["隨機轉光"]},
{"no":"1834","tag":["全轉火","全轉水","全轉木","全轉闇"]},
{"no":"1835","tag":["全轉火","全轉水","全轉木","全轉闇"]},
{"no":"1838","tag":["全轉火","全轉水","全轉木","全轉光","全轉暗","全轉回復","全轉邪魔"]},
{"no":"1839","tag":["全轉火","全轉水","全轉木","全轉光","全轉暗","全轉回復","全轉邪魔"]},
{"no":"1840","tag":["全轉火","全轉水","全轉木","全轉光","全轉闇"]},
{"no":"1841","tag":["全轉火","全轉水","全轉木","全轉光","全轉闇"]},
{"no":"1842","tag":["全轉火","全轉水","全轉木","全轉光","全轉暗","全轉回復","全轉毒"]},
{"no":"1843","tag":["全轉火","全轉水","全轉木","全轉光","全轉暗","全轉回復","全轉毒"]},
{"no":"1848","tag":["闇轉光"]},
{"no":"1849","tag":["光轉闇"]},
{"no":"1851","tag":["隨機轉闇"]},
{"no":"1853","tag":["隨機轉闇"]},
{"no":"1855","tag":["横轉回復"]},
{"no":"1858","tag":["回復轉火","邪魔轉火","毒轉火"]},
{"no":"1859","tag":["回復轉火","邪魔轉火","毒轉火"]},
{"no":"1864","tag":["隨機轉光"]},
{"no":"1865","tag":["隨機轉光"]},
{"no":"1866","tag":["回復轉水","邪魔轉水","毒轉水"]},
{"no":"1867","tag":["回復轉水","邪魔轉水","毒轉水"]},
{"no":"1868","tag":["隨機轉木","隨機轉闇"]},
{"no":"1869","tag":["隨機轉木","隨機轉闇"]},
{"no":"1872","tag":["横轉光","縦轉光"]},
{"no":"1873","tag":["横轉光","縦轉光"]},
{"no":"1874","tag":["邪魔轉火","水轉火"]},
{"no":"1875","tag":["邪魔轉火","水轉火"]},
{"no":"1878","tag":["隨機轉光"]},
{"no":"1879","tag":["隨機轉光"]},
{"no":"1880","tag":["闇轉水","木轉回復"]},
{"no":"1891","tag":["回復轉火","邪魔轉火","毒轉火"]},
{"no":"1896","tag":["回復轉木"]},
{"no":"1897","tag":["回復轉木"]},
{"no":"1898","tag":["回復轉闇"]},
{"no":"1899","tag":["回復轉闇"]},
{"no":"1900","tag":["全轉木","全轉光","全轉闇","全轉回復"]},
{"no":"1901","tag":["全轉木","全轉光","全轉闇","全轉回復"]},
{"no":"1904","tag":["隨機轉火"]},
{"no":"1908","tag":["隨機轉火"]},
{"no":"1914","tag":["縦轉光","縦轉闇"]},
{"no":"1915","tag":["縦轉光","縦轉闇"]},
{"no":"1917","tag":["横轉火"]},
{"no":"1938","tag":["隨機轉火","隨機轉水"]},
{"no":"1942","tag":["火轉闇","邪魔轉闇","毒轉闇"]},
{"no":"1944","tag":["隨機轉木"]},
{"no":"1945","tag":["隨機轉木"]},
{"no":"1946","tag":["全轉火","全轉光","全轉闇","全轉回復"]},
{"no":"1947","tag":["全轉火","全轉光","全轉闇","全轉回復"]},
{"no":"1948","tag":["全轉火","全轉水","全轉闇","全轉回復"]},
{"no":"1949","tag":["全轉火","全轉水","全轉闇","全轉回復"]},
{"no":"1950","tag":["全轉火","全轉光"]},
{"no":"1951","tag":["全轉火","全轉光"]},
{"no":"1952","tag":["全轉火","全轉木","全轉闇"]},
{"no":"1953","tag":["全轉火","全轉木","全轉闇"]},
{"no":"1955","tag":["隨機轉回復"]},
{"no":"1956","tag":["水轉回復"]},
{"no":"1962","tag":["回復轉火"]},
{"no":"1963","tag":["縦轉水"]},
{"no":"1964","tag":["縦轉木"]},
{"no":"1967","tag":["光轉木","回復轉光"]},
{"no":"1968","tag":["光轉木","回復轉光"]},
{"no":"1969","tag":["光轉木","回復轉光"]},
{"no":"1970","tag":["全轉火","全轉水","全轉木","全轉闇","全轉回復"]},
{"no":"1971","tag":["全轉火","全轉水","全轉木","全轉闇","全轉回復"]},
{"no":"1972","tag":["全轉火","全轉光","全轉回復"]},
{"no":"1973","tag":["全轉火","全轉光","全轉回復"]},
{"no":"1987","tag":["木轉回復","光轉回復","毒轉回復"]},
{"no":"1989","tag":["火轉回復","闇轉回復","毒轉回復"]},
{"no":"1991","tag":["水轉回復","光轉回復","毒轉回復"]},
{"no":"1993","tag":["火轉回復","光轉回復","毒轉回復"]},
{"no":"1994","tag":["全轉火","全轉水","全轉木","全轉闇","全轉回復"]},
{"no":"1995","tag":["全轉火","全轉光","全轉回復"]},
{"no":"2004","tag":["木轉回復","闇轉回復","毒轉回復"]},
{"no":"2006","tag":["全轉火"]},
{"no":"2013","tag":["木轉闇","邪魔轉闇","毒轉闇"]},
{"no":"2014","tag":["隨機轉回復"]},
{"no":"2019","tag":["回復轉火"]},
{"no":"2020","tag":["光轉火"]},
{"no":"2024","tag":["木轉火","闇轉回復"]},
{"no":"2025","tag":["火轉水","光轉回復"]},
{"no":"2026","tag":["水轉木","火轉回復"]},
{"no":"2027","tag":["水轉光","闇轉回復"]},
{"no":"2028","tag":["木轉闇","光轉回復"]},
{"no":"2029","tag":["縦轉光"]},
{"no":"2030","tag":["縦轉光"]},
{"no":"2033","tag":["回復轉火","邪魔轉火"]},
{"no":"2034","tag":["回復轉火","邪魔轉火"]},
{"no":"2051","tag":["全轉火","全轉水","全轉木","全轉光","全轉闇","全轉回復"]},
{"no":"2060","tag":["縦轉光"]},
{"no":"2062","tag":["回復轉火","邪魔轉火"]},
{"no":"2071","tag":["闇轉水","回復轉水"]},
{"no":"2073","tag":["全轉火","全轉木","全轉光"]},
{"no":"2074","tag":["全轉水","全轉木","全轉闇"]},
{"no":"2075","tag":["全轉木","全轉光","全轉闇"]},
{"no":"2076","tag":["全轉火","全轉水","全轉闇"]},
{"no":"2078","tag":["全轉火","全轉水","全轉木","全轉光","全轉暗","全轉回復"]},
{"no":"2079","tag":["隨機轉火"]},
{"no":"2080","tag":["隨機轉水"]},
{"no":"2081","tag":["隨機轉木"]},
{"no":"2084","tag":["全轉火","全轉水","全轉木","全轉光","全轉闇","全轉回復"]},
{"no":"2095","tag":["隨機轉回復"]},
{"no":"2096","tag":["隨機轉回復"]},
{"no":"2097","tag":["隨機轉木"]},
{"no":"2098","tag":["隨機轉木"]},
{"no":"2099","tag":["隨機轉回復"]},
{"no":"2100","tag":["隨機轉回復"]},
{"no":"2103","tag":["隨機轉水"]},
{"no":"2104","tag":["隨機轉水"]},
{"no":"2105","tag":["隨機轉光"]},
{"no":"2106","tag":["回復轉木"]},
{"no":"2107","tag":["回復轉木"]},
{"no":"2124","tag":["回復轉光","闇轉回復"]},
{"no":"2125","tag":["隨機轉光"]},
{"no":"2126","tag":["隨機轉光"]},
{"no":"2135","tag":["闇轉火","光轉水"]},
{"no":"2136","tag":["闇轉火","光轉水"]},
{"no":"2137","tag":["光轉毒"]},
{"no":"2138","tag":["光轉毒"]},
{"no":"2141","tag":["隨機轉火","隨機轉光"]},
{"no":"2142","tag":["隨機轉火","隨機轉光"]},
{"no":"2143","tag":["隨機轉水","隨機轉回復"]},
{"no":"2144","tag":["隨機轉水","隨機轉回復"]},
{"no":"2145","tag":["隨機轉木","隨機轉回復"]},
{"no":"2146","tag":["隨機轉木","隨機轉回復"]},
{"no":"2149","tag":["水轉闇","邪魔轉闇","毒轉闇"]},
{"no":"2150","tag":["水轉闇","邪魔轉闇","毒轉闇"]},
{"no":"2151","tag":["隨機轉光"]},
{"no":"2152","tag":["隨機轉闇"]},
{"no":"2156","tag":["隨機轉回復"]},
{"no":"2158","tag":["隨機轉木"]},
{"no":"2160","tag":["隨機轉回復"]},
{"no":"2167","tag":["縦轉火"]},
{"no":"2168","tag":["縦轉火"]},
{"no":"2173","tag":["毒轉光","水轉光"]},
{"no":"2174","tag":["毒轉光","水轉光"]},
{"no":"2175","tag":["横轉闇"]},
{"no":"2176","tag":["横轉闇"]},
{"no":"2178","tag":["横轉闇"]},
{"no":"2181","tag":["全轉火","全轉水","全轉光","全轉闇"]},
{"no":"2182","tag":["全轉火","全轉水","全轉光","全轉闇"]},
{"no":"2185","tag":["横轉火"]},
{"no":"2186","tag":["横轉水"]},
{"no":"2187","tag":["横轉木"]},
{"no":"2188","tag":["横轉光"]},
{"no":"2189","tag":["横轉闇"]},
{"no":"2190","tag":["縦轉火"]},
{"no":"2191","tag":["縦轉水"]},
{"no":"2192","tag":["縦轉木"]},
{"no":"2193","tag":["縦轉光"]},
{"no":"2194","tag":["縦轉闇"]},
{"no":"2195","tag":["縦轉火"]},
{"no":"2196","tag":["縦轉水"]},
{"no":"2197","tag":["縦轉木"]},
{"no":"2198","tag":["縦轉光"]},
{"no":"2199","tag":["縦轉闇"]},
{"no":"2201","tag":["縦轉火"]},
{"no":"2204","tag":["毒轉光","水轉光"]},
{"no":"2205","tag":["隨機轉火"]},
{"no":"2206","tag":["隨機轉火"]},
{"no":"2218","tag":["全轉水","全轉木","全轉回復"]},
{"no":"2220","tag":["回復轉木","邪魔轉木"]},
{"no":"2224","tag":["回復轉木","邪魔轉木"]},
{"no":"2225","tag":["全轉水","全轉木","全轉回復"]},
{"no":"2229","tag":["全轉火","全轉木","全轉光","全轉闇","全轉回復"]},
{"no":"2230","tag":["全轉火","全轉木","全轉光","全轉闇","全轉回復"]},
{"no":"2231","tag":["全轉火","全轉木","全轉光","全轉回復"]},
{"no":"2232","tag":["全轉火","全轉木","全轉光","全轉回復"]},
{"no":"2235","tag":["水轉火","回復轉火"]},
{"no":"2236","tag":["木轉水","回復轉水"]},
{"no":"2237","tag":["火轉木","回復轉木"]},
{"no":"2238","tag":["闇轉光","回復轉光"]},
{"no":"2239","tag":["光轉闇","回復轉闇"]},
{"no":"2241","tag":["隨機轉回復"]},
{"no":"2242","tag":["隨機轉回復"]},
{"no":"2243","tag":["隨機轉回復"]},
{"no":"2244","tag":["隨機轉光","隨機轉闇"]},
{"no":"2245","tag":["隨機轉光","隨機轉闇"]},
{"no":"2249","tag":["全轉火","全轉水","全轉木","全轉闇","全轉回復"]},
{"no":"2260","tag":["隨機轉闇","隨機轉回復"]},
{"no":"2261","tag":["隨機轉闇","隨機轉回復"]},
{"no":"2262","tag":["隨機轉水","隨機轉闇"]},
{"no":"2263","tag":["隨機轉水","隨機轉闇"]},
{"no":"2264","tag":["水轉火","光轉回復"]},
{"no":"2265","tag":["水轉火","光轉回復"]},
{"no":"2266","tag":["全轉火","全轉水"]},
{"no":"2267","tag":["全轉火","全轉水"]},
{"no":"2268","tag":["全轉木","全轉闇","全轉回復"]},
{"no":"2269","tag":["全轉木","全轉闇","全轉回復"]},
{"no":"2272","tag":["火轉闇","水轉回復"]},
{"no":"2273","tag":["火轉闇","水轉回復"]},
{"no":"2274","tag":["隨機轉光","隨機轉闇"]},
{"no":"2276","tag":["隨機轉水","隨機轉回復"]},
{"no":"2277","tag":["隨機轉水","隨機轉回復"]},
{"no":"2279","tag":["火轉水","回復轉木"]},
{"no":"2284","tag":["全轉水","全轉木"]},
{"no":"2285","tag":["邪魔轉回復","毒轉回復"]},
{"no":"2287","tag":["全轉水","全轉木"]},
{"no":"2288","tag":["全轉火","全轉水","全轉回復"]},
{"no":"2289","tag":["全轉火","全轉水","全轉回復"]},
{"no":"2290","tag":["回復轉闇"]},
{"no":"2291","tag":["邪魔轉回復","毒轉回復"]},
{"no":"2292","tag":["木轉闇","光轉回復"]},
{"no":"2299","tag":["全轉火","全轉水","全轉木","全轉光","全轉暗","全轉回復","全轉邪魔"]},
{"no":"2300","tag":["火轉邪魔","回復轉邪魔"]},
{"no":"2302","tag":["闇轉回復","邪魔轉回復","毒轉回復"]},
{"no":"2303","tag":["全轉火","全轉水","全轉木","全轉光","全轉暗","全轉回復"]},
{"no":"2305","tag":["光轉回復"]},
{"no":"2307","tag":["全轉水","全轉木","全轉光","全轉闇"]},
{"no":"2309","tag":["隨機轉木","隨機轉闇"]},
{"no":"2311","tag":["隨機轉光"]},
{"no":"2313","tag":["全轉火","全轉水","全轉木","全轉闇"]},
{"no":"2317","tag":["全轉火","全轉闇"]},
{"no":"2318","tag":["回復轉闇"]},
{"no":"2319","tag":["闇轉木","火轉光"]},
{"no":"2320","tag":["闇轉木","火轉光"]},
{"no":"2321","tag":["回復轉光"]},
{"no":"2326","tag":["木轉水","回復轉闇"]},
{"no":"2328","tag":["闇轉火","回復轉火"]},
{"no":"2329","tag":["木轉水","回復轉闇"]},
{"no":"2332","tag":["闇轉火","回復轉火"]},
{"no":"2333","tag":["横轉火"]},
{"no":"2334","tag":["横轉水"]},
{"no":"2336","tag":["横轉木"]},
{"no":"2337","tag":["横轉光"]},
{"no":"2338","tag":["横轉闇"]},
{"no":"2343","tag":["全轉火","全轉木"]},
{"no":"2349","tag":["全轉火","全轉木"]},
{"no":"2356","tag":["隨機轉水"]},
{"no":"2357","tag":["隨機轉水"]},
{"no":"2358","tag":["全轉火","全轉水","全轉光","全轉闇","全轉回復"]},
{"no":"2359","tag":["全轉火","全轉水","全轉光","全轉闇","全轉回復"]},
{"no":"2360","tag":["全轉火","全轉水","全轉光","全轉闇","全轉回復"]},
{"no":"2363","tag":["火轉光","邪魔轉光","毒轉光"]},
{"no":"2364","tag":["火轉光","邪魔轉光","毒轉光"]},
{"no":"2380","tag":["隨機轉水"]},
{"no":"2381","tag":["全轉火","全轉水","全轉光","全轉闇","全轉回復"]},
{"no":"2384","tag":["回復轉火"]},
{"no":"2385","tag":["縦轉水"]},
{"no":"2386","tag":["縦轉木"]},
{"no":"2390","tag":["全轉火","全轉木","全轉回復"]},
{"no":"2391","tag":["全轉水"]},
{"no":"2397","tag":["全轉火"]},
{"no":"2398","tag":["全轉火"]},
{"no":"2401","tag":["火轉回復","火轉毒","水轉回復","水轉毒"]},
{"no":"2402","tag":["火轉回復","火轉毒","水轉回復","水轉毒"]},
{"no":"2404","tag":["全轉水","全轉闇"]},
{"no":"2405","tag":["横轉闇"]},
{"no":"2406","tag":["全轉水","全轉闇"]},
{"no":"2407","tag":["全轉火","全轉水","全轉木","全轉光","全轉闇"]},
{"no":"2409","tag":["横轉闇"]},
{"no":"2410","tag":["回復轉闇"]},
{"no":"2412","tag":["水轉回復"]},
{"no":"2413","tag":["全轉火","全轉木","全轉闇"]},
{"no":"2415","tag":["回復轉火","邪魔轉火","毒轉火"]},
{"no":"2416","tag":["回復轉火","邪魔轉火","毒轉火"]},
{"no":"2417","tag":["回復轉水","邪魔轉水","毒轉水"]},
{"no":"2418","tag":["回復轉水","邪魔轉水","毒轉水"]},
{"no":"2419","tag":["回復轉木","邪魔轉木","毒轉木"]},
{"no":"2420","tag":["回復轉木","邪魔轉木","毒轉木"]},
{"no":"2421","tag":["回復轉光","邪魔轉光","毒轉光"]},
{"no":"2422","tag":["回復轉光","邪魔轉光","毒轉光"]},
{"no":"2423","tag":["回復轉闇","邪魔轉闇","毒轉闇"]},
{"no":"2424","tag":["回復轉闇","邪魔轉闇","毒轉闇"]},
{"no":"2426","tag":["全轉水","全轉木","全轉光"]},
{"no":"2427","tag":["全轉水","全轉木","全轉光"]},
{"no":"2431","tag":["全轉木","全轉光"]},
{"no":"2432","tag":["回復轉毒"]},
{"no":"2433","tag":["全轉光","全轉闇","全轉回復"]},
{"no":"2434","tag":["全轉回復"]},
{"no":"2435","tag":["水轉火","光轉回復"]},
{"no":"2436","tag":["全轉火","全轉水"]},
{"no":"2437","tag":["全轉木","全轉闇","全轉回復"]},
{"no":"2439","tag":["火轉闇","水轉回復"]},
{"no":"2440","tag":["全轉火","全轉光","全轉回復"]},
{"no":"2441","tag":["全轉火","全轉光","全轉回復"]},
{"no":"2442","tag":["全轉水","全轉闇","全轉回復"]},
{"no":"2443","tag":["全轉水","全轉闇","全轉回復"]},
{"no":"2445","tag":["回復轉火","邪魔轉火","毒轉火"]},
{"no":"2446","tag":["隨機轉回復"]},
{"no":"2447","tag":["隨機轉回復"]},
{"no":"2455","tag":["隨機轉回復"]},
{"no":"2457","tag":["全轉火","全轉木","全轉光","全轉闇","全轉回復"]},
{"no":"2458","tag":["全轉火","全轉木","全轉光","全轉闇","全轉回復"]},
{"no":"2459","tag":["全轉火","全轉木","全轉光","全轉闇","全轉回復"]},
{"no":"2464","tag":["回復轉光","邪魔轉光","毒轉光"]},
{"no":"2465","tag":["回復轉光","邪魔轉光","毒轉光"]},
{"no":"2468","tag":["隨機轉火"]},
{"no":"2469","tag":["隨機轉火"]},
{"no":"2470","tag":["隨機轉木"]},
{"no":"2471","tag":["隨機轉木"]},
{"no":"2472","tag":["回復轉光","毒轉光"]},
{"no":"2473","tag":["回復轉光","毒轉光"]},
{"no":"2474","tag":["全轉火","全轉光","全轉回復"]},
{"no":"2475","tag":["全轉火","全轉光","全轉回復"]},
{"no":"2476","tag":["回復轉火","毒轉火"]},
{"no":"2477","tag":["回復轉火","毒轉火"]},
{"no":"2478","tag":["隨機轉闇","隨機轉邪魔"]},
{"no":"2479","tag":["隨機轉闇","隨機轉邪魔"]},
{"no":"2482","tag":["全轉火","全轉木","全轉闇","全轉毒"]},
{"no":"2483","tag":["全轉火","全轉木","全轉闇","全轉毒"]},
{"no":"2487","tag":["全轉火","全轉木","全轉光","全轉闇","全轉回復"]},
{"no":"2488","tag":["隨機轉火"]},
{"no":"2489","tag":["回復轉光","毒轉光"]},
{"no":"2490","tag":["全轉火","全轉光","全轉回復"]},
{"no":"2491","tag":["回復轉光","邪魔轉光","毒轉光"]},
{"no":"2493","tag":["光轉回復"]},
{"no":"2494","tag":["全轉水","全轉木","全轉光","全轉闇"]},
{"no":"2495","tag":["隨機轉木","隨機轉闇"]},
{"no":"2496","tag":["隨機轉光"]},
{"no":"2497","tag":["全轉火","全轉水","全轉木","全轉闇"]},
{"no":"2498","tag":["光轉火","闇轉回復"]},
{"no":"2499","tag":["光轉水","闇轉回復"]},
{"no":"2500","tag":["光轉木","闇轉回復"]},
{"no":"2501","tag":["全轉回復"]},
{"no":"2502","tag":["隨機轉回復"]},
{"no":"2503","tag":["木轉火"]},
{"no":"2504","tag":["火轉水"]},
{"no":"2505","tag":["火轉木","邪魔轉木","毒轉木"]},
{"no":"2506","tag":["水轉光"]},
{"no":"2507","tag":["隨機轉闇"]},
{"no":"2508","tag":["全轉木","全轉光","全轉回復"]},
{"no":"2509","tag":["全轉木","全轉光","全轉回復"]},
{"no":"2511","tag":["全轉火","全轉水","全轉木","全轉光","全轉暗","全轉回復"]},
{"no":"2512","tag":["全轉火","全轉木"]},
{"no":"2513","tag":["全轉火","全轉水","全轉闇"]},
{"no":"2514","tag":["闇轉火","回復轉火"]},
{"no":"2520","tag":["隨機轉水"]},
{"no":"2521","tag":["全轉火","全轉木"]},
{"no":"2522","tag":["闇轉火","回復轉火"]},
{"no":"2531","tag":["水轉火","回復轉闇"]},
{"no":"2535","tag":["全轉火","全轉木","全轉光"]},
{"no":"2536","tag":["木轉火","闇轉回復"]},
{"no":"2538","tag":["火轉光"]},
{"no":"2539","tag":["隨機轉光"]},
{"no":"2543","tag":["木轉回復","闇轉回復"]},
{"no":"2545","tag":["火轉光"]},
{"no":"2547","tag":["隨機轉光"]},
{"no":"2552","tag":["隨機轉火","隨機轉邪魔"]},
{"no":"2553","tag":["隨機轉火","隨機轉邪魔"]},
{"no":"2554","tag":["隨機轉水","隨機轉邪魔"]},
{"no":"2555","tag":["隨機轉水","隨機轉邪魔"]},
{"no":"2556","tag":["隨機轉木","隨機轉邪魔"]},
{"no":"2557","tag":["隨機轉木","隨機轉邪魔"]},
{"no":"2558","tag":["闇轉光","回復轉光","毒轉光"]},
{"no":"2559","tag":["闇轉光","回復轉光","毒轉光"]},
{"no":"2560","tag":["光轉闇","回復轉闇","毒轉闇"]},
{"no":"2561","tag":["光轉闇","回復轉闇","毒轉闇"]},
{"no":"2562","tag":["光轉木","回復轉木","邪魔轉木","毒轉木"]},
{"no":"2563","tag":["光轉木","回復轉木","邪魔轉木","毒轉木"]},
{"no":"2564","tag":["光轉水","回復轉水","邪魔轉水","毒轉水"]},
{"no":"2565","tag":["光轉水","回復轉水","邪魔轉水","毒轉水"]},
{"no":"2566","tag":["全轉水","全轉闇"]},
{"no":"2567","tag":["全轉木","全轉闇"]},
{"no":"2570","tag":["全轉火","全轉闇"]},
{"no":"2572","tag":["全轉火","全轉水","全轉木","全轉光","全轉闇"]},
{"no":"2574","tag":["木轉回復","闇轉回復"]},
{"no":"2575","tag":["木轉火"]},
{"no":"2576","tag":["火轉木"]},
{"no":"2578","tag":["水轉光"]},
{"no":"2579","tag":["火轉水"]},
{"no":"2580","tag":["木轉闇"]},
{"no":"2582","tag":["闇轉火"]},
{"no":"2591","tag":["木轉闇","回復轉闇","邪魔轉闇","毒轉闇"]},
{"no":"2592","tag":["木轉闇","回復轉闇","邪魔轉闇","毒轉闇"]},
{"no":"2593","tag":["全轉火","全轉水","全轉木","全轉光","全轉暗","全轉回復"]},
{"no":"2594","tag":["全轉火","全轉水","全轉木","全轉光","全轉暗","全轉回復"]},
{"no":"2596","tag":["縦轉火"]},
{"no":"2597","tag":["毒轉光","水轉光"]},
{"no":"2600","tag":["全轉火","全轉闇"]},
{"no":"2601","tag":["回復轉火","邪魔轉火","毒轉火"]},
{"no":"2602","tag":["回復轉火","邪魔轉火","毒轉火"]},
{"no":"2603","tag":["隨機轉火","隨機轉回復"]},
{"no":"2604","tag":["隨機轉火","隨機轉回復"]},
{"no":"2607","tag":["隨機轉闇"]},
{"no":"2608","tag":["隨機轉闇"]},
{"no":"2613","tag":["回復轉闇","光轉邪魔"]},
{"no":"2614","tag":["回復轉闇","光轉邪魔"]},
{"no":"2619","tag":["隨機轉闇"]},
{"no":"2620","tag":["隨機轉闇"]},
{"no":"2621","tag":["光轉邪魔"]},
{"no":"2622","tag":["光轉邪魔"]},
{"no":"2631","tag":["回復轉火","邪魔轉火","毒轉火"]},
{"no":"2632","tag":["隨機轉火","隨機轉回復"]},
{"no":"2634","tag":["隨機轉闇"]},
{"no":"2636","tag":["毒轉邪魔"]},
{"no":"2637","tag":["毒轉邪魔"]},
{"no":"2638","tag":["全轉火","全轉水","全轉木","全轉光","全轉暗","全轉邪魔"]},
{"no":"2639","tag":["全轉火","全轉水","全轉木","全轉光","全轉暗","全轉邪魔"]},
{"no":"2640","tag":["隨機轉闇","隨機轉邪魔"]},
{"no":"2641","tag":["隨機轉闇","隨機轉邪魔"]},
{"no":"2642","tag":["回復轉火","邪魔轉火","毒轉火"]},
{"no":"2643","tag":["回復轉水","邪魔轉水","毒轉水"]},
{"no":"2644","tag":["回復轉木","邪魔轉木","毒轉木"]},
{"no":"2645","tag":["回復轉光","邪魔轉光","毒轉光"]},
{"no":"2646","tag":["回復轉闇","邪魔轉闇","毒轉闇"]},
{"no":"2647","tag":["隨機轉火","隨機轉邪魔"]},
{"no":"2648","tag":["隨機轉水","隨機轉邪魔"]},
{"no":"2649","tag":["隨機轉木","隨機轉邪魔"]},
{"no":"2650","tag":["闇轉光","回復轉光","毒轉光"]},
{"no":"2651","tag":["光轉闇","回復轉闇","毒轉闇"]},
{"no":"2657","tag":["木轉火","闇轉回復"]},
{"no":"2658","tag":["火轉水","光轉回復"]},
{"no":"2659","tag":["水轉木","火轉回復"]},
{"no":"2660","tag":["水轉光","闇轉回復"]},
{"no":"2661","tag":["木轉闇","光轉回復"]},
{"no":"2662","tag":["木轉闇","光轉回復"]},
{"no":"2663","tag":["全轉火","全轉水","全轉回復"]},
{"no":"2675","tag":["全轉火","全轉水","全轉木","全轉光","全轉暗","全轉回復"]},
{"no":"2676","tag":["全轉火","全轉水","全轉木","全轉光","全轉暗","全轉回復"]},
{"no":"2677","tag":["全轉火","全轉水","全轉木","全轉光","全轉暗","全轉回復"]},
{"no":"2678","tag":["縦轉水"]},
{"no":"2679","tag":["縦轉水"]},
{"no":"2680","tag":["隨機轉回復"]},
{"no":"2681","tag":["隨機轉回復"]},
{"no":"2682","tag":["隨機轉光"]},
{"no":"2683","tag":["隨機轉光"]},
{"no":"2684","tag":["横轉火","横轉火"]},
{"no":"2685","tag":["横轉火","横轉火"]},
{"no":"2688","tag":["横轉木","隨機轉邪魔"]},
{"no":"2689","tag":["横轉木","隨機轉邪魔"]},
{"no":"2690","tag":["全轉水"]},
{"no":"2691","tag":["全轉水"]},
{"no":"2696","tag":["隨機轉木","隨機轉回復"]},
{"no":"2697","tag":["隨機轉木","隨機轉回復"]},
{"no":"2698","tag":["隨機轉火"]},
{"no":"2699","tag":["隨機轉火"]},
{"no":"2700","tag":["隨機轉毒"]},
{"no":"2701","tag":["隨機轉毒"]},
{"no":"2705","tag":["全轉火","全轉水","全轉木","全轉光","全轉暗","全轉回復"]},
{"no":"2706","tag":["縦轉水"]},
{"no":"2707","tag":["横轉木","隨機轉邪魔"]},
{"no":"2708","tag":["全轉水"]},
{"no":"2710","tag":["全轉火","全轉水","全轉木","全轉光","全轉闇"]},
{"no":"2711","tag":["全轉火","全轉水","全轉木","全轉光","全轉闇"]},
{"no":"2714","tag":["全轉水","全轉木","全轉回復"]},
{"no":"2716","tag":["光轉火","闇轉邪魔"]},
{"no":"2717","tag":["全轉水"]},
{"no":"2718","tag":["全轉火","全轉水","全轉木","全轉光","全轉暗","全轉回復"]},
{"no":"2720","tag":["隨機轉闇","隨機轉回復"]},
{"no":"2721","tag":["火轉邪魔","闇轉邪魔"]},
{"no":"2722","tag":["火轉邪魔","闇轉邪魔"]},
{"no":"2723","tag":["隨機轉火"]},
{"no":"2724","tag":["隨機轉水"]},
{"no":"2725","tag":["隨機轉木"]},
{"no":"2726","tag":["全轉火","全轉水","全轉木","全轉光"]},
{"no":"2727","tag":["隨機轉闇"]},
{"no":"2728","tag":["光轉闇","邪魔轉闇","回復轉光","毒轉光"]},
{"no":"2729","tag":["光轉闇","邪魔轉闇","回復轉光","毒轉光"]},
{"no":"2730","tag":["横轉回復"]},
{"no":"2731","tag":["横轉回復"]},
{"no":"2732","tag":["全轉火","全轉水","全轉木","全轉光","全轉闇"]},
{"no":"2733","tag":["全轉火","全轉水","全轉木","全轉光","全轉闇"]},
{"no":"2734","tag":["隨機轉光"]},
{"no":"2735","tag":["隨機轉光"]},
{"no":"2739","tag":["水轉火"]},
{"no":"2740","tag":["木轉水"]},
{"no":"2741","tag":["火轉木"]},
{"no":"2742","tag":["闇轉光"]},
{"no":"2743","tag":["光轉闇"]},
{"no":"2744","tag":["全轉火","全轉光","全轉闇","全轉回復"]},
{"no":"2745","tag":["全轉火","全轉水","全轉闇","全轉回復"]},
{"no":"2746","tag":["全轉火","全轉木","全轉闇"]},
{"no":"2747","tag":["水轉火","回復轉火"]},
{"no":"2748","tag":["木轉水","回復轉水"]},
{"no":"2749","tag":["火轉木","回復轉木"]},
{"no":"2750","tag":["闇轉光","回復轉光"]},
{"no":"2751","tag":["光轉闇","回復轉闇"]},
{"no":"2752","tag":["全轉木","全轉光"]},
{"no":"2753","tag":["水轉回復","光轉猛毒"]},
{"no":"2754","tag":["水轉回復","光轉猛毒"]},
{"no":"2755","tag":["隨機轉回復"]},
{"no":"2756","tag":["隨機轉回復"]},
{"no":"2757","tag":["隨機轉水"]},
{"no":"2758","tag":["隨機轉水"]},
{"no":"2759","tag":["隨機轉光"]},
{"no":"2760","tag":["隨機轉光"]},
{"no":"2761","tag":["隨機轉闇","隨機轉回復"]},
{"no":"2762","tag":["隨機轉闇","隨機轉回復"]},
{"no":"2763","tag":["隨機轉回復"]},
{"no":"2764","tag":["縦轉光"]},
{"no":"2767","tag":["全轉光","全轉闇","全轉回復"]},
{"no":"2768","tag":["全轉光","全轉闇","全轉回復"]},
{"no":"2769","tag":["全轉光","全轉闇","全轉回復"]},
{"no":"2770","tag":["縦轉木"]},
{"no":"2771","tag":["縦轉木"]},
{"no":"2772","tag":["縦轉火","縦轉光"]},
{"no":"2773","tag":["縦轉火","縦轉光"]},
{"no":"2774","tag":["横轉闇","横轉木"]},
{"no":"2775","tag":["横轉闇","横轉木"]},
{"no":"2776","tag":["横轉光","横轉火"]},
{"no":"2777","tag":["横轉光","横轉火"]},
{"no":"2778","tag":["全轉火","全轉水","全轉木","全轉光","全轉暗","全轉回復"]},
{"no":"2779","tag":["全轉火","全轉水","全轉木","全轉光","全轉暗","全轉回復"]},
{"no":"2780","tag":["全轉火","全轉水","全轉木","全轉光","全轉暗","全轉回復"]},
{"no":"2781","tag":["闇轉水","火轉回復"]},
{"no":"2782","tag":["闇轉水","火轉回復"]},
{"no":"2785","tag":["回復轉邪魔"]},
{"no":"2786","tag":["隨機轉火"]},
{"no":"2792","tag":["全轉光","全轉闇","全轉回復"]},
{"no":"2793","tag":["縦轉木"]},
{"no":"2794","tag":["縦轉火","縦轉光"]},
{"no":"2795","tag":["横轉闇","横轉木"]},
{"no":"2796","tag":["横轉光","横轉火"]},
{"no":"2797","tag":["全轉火","全轉水","全轉木","全轉光","全轉暗","全轉回復"]},
{"no":"2798","tag":["闇轉水","火轉回復"]},
{"no":"2800","tag":["隨機轉火"]},
{"no":"2803","tag":["全轉木","全轉光","全轉闇","全轉回復"]},
{"no":"2804","tag":["隨機轉邪魔"]},
{"no":"2805","tag":["隨機轉邪魔"]},
{"no":"2808","tag":["隨機轉木"]},
{"no":"2814","tag":["全轉火","全轉水","全轉木","全轉光","全轉暗","全轉回復"]},
{"no":"2815","tag":["光轉水"]},
{"no":"2821","tag":["隨機轉火"]},
{"no":"2822","tag":["光轉水"]},
{"no":"2824","tag":["全轉火","全轉水","全轉光"]},
{"no":"2826","tag":["全轉木","全轉闇","全轉回復"]},
{"no":"2827","tag":["全轉木","全轉闇","全轉回復"]},
{"no":"2828","tag":["闇轉光","邪魔轉光","回復轉闇","毒轉闇"]},
{"no":"2829","tag":["光轉闇","邪魔轉闇","回復轉光","毒轉光"]},
{"no":"2832","tag":["光轉邪魔"]},
{"no":"2833","tag":["光轉邪魔"]},
{"no":"2834","tag":["全轉火","全轉水","全轉光"]},
{"no":"2835","tag":["縦轉光","縦轉水"]},
{"no":"2836","tag":["全轉木","全轉闇","全轉回復"]},
{"no":"2837","tag":["隨機轉木","隨機轉邪魔"]},
{"no":"2838","tag":["隨機轉木","隨機轉邪魔"]},
{"no":"2839","tag":["全轉水","全轉光","全轉闇","全轉回復"]},
{"no":"2840","tag":["全轉水","全轉光","全轉闇","全轉回復"]},
{"no":"2843","tag":["隨機轉闇"]},
{"no":"2844","tag":["隨機轉闇"]},
{"no":"2845","tag":["隨機轉火"]},
{"no":"2846","tag":["隨機轉火"]},
{"no":"2847","tag":["隨機轉水"]},
{"no":"2848","tag":["隨機轉水"]},
{"no":"2849","tag":["隨機轉光"]},
{"no":"2850","tag":["隨機轉光"]},
{"no":"2851","tag":["隨機轉闇"]},
{"no":"2852","tag":["隨機轉闇"]},
{"no":"2855","tag":["光轉木","毒轉木"]},
{"no":"2856","tag":["光轉木","毒轉木"]},
{"no":"2857","tag":["闇轉水","毒轉水"]},
{"no":"2858","tag":["闇轉水","毒轉水"]},
{"no":"2861","tag":["全轉水","全轉木","全轉光"]},
{"no":"2862","tag":["全轉水","全轉木","全轉光"]},
{"no":"2867","tag":["木轉闇","光轉毒"]},
{"no":"2868","tag":["木轉闇","光轉毒"]},
{"no":"2869","tag":["全轉水","全轉光","全轉闇","全轉回復"]},
{"no":"2870","tag":["隨機轉火"]},
{"no":"2873","tag":["全轉水","全轉木","全轉光"]},
{"no":"2874","tag":["隨機轉闇"]},
{"no":"2875","tag":["全轉火","全轉光","全轉闇","全轉回復"]},
{"no":"2876","tag":["全轉水","全轉闇","全轉回復"]},
{"no":"2877","tag":["全轉木","全轉光","全轉回復"]},
{"no":"2878","tag":["全轉火","全轉光","全轉回復"]},
{"no":"2879","tag":["全轉火","全轉水","全轉闇","全轉回復"]},
{"no":"2881","tag":["隨機轉回復"]},
{"no":"2882","tag":["隨機轉木"]},
{"no":"2883","tag":["隨機轉回復"]},
{"no":"2890","tag":["隨機轉光"]},
{"no":"2891","tag":["隨機轉光"]},
{"no":"2893","tag":["火轉回復","火轉毒","水轉回復","水轉毒"]},
{"no":"2894","tag":["全轉火","全轉木","全轉闇"]},
{"no":"2895","tag":["毒轉邪魔"]},
{"no":"2896","tag":["毒轉邪魔"]},
{"no":"2897","tag":["全轉光","全轉回復","全轉邪魔"]},
{"no":"2898","tag":["全轉光","全轉回復","全轉邪魔"]},
{"no":"2899","tag":["火轉邪魔","回復轉邪魔"]},
{"no":"2900","tag":["火轉邪魔","回復轉邪魔"]},
{"no":"2901","tag":["水轉火","毒轉火"]},
{"no":"2903","tag":["闇轉木","回復轉木"]},
{"no":"2904","tag":["闇轉光","火轉回復","邪魔轉水","毒轉水"]},
{"no":"2906","tag":["回復轉闇"]},
{"no":"2907","tag":["全轉火","全轉水","全轉回復"]},
{"no":"2908","tag":["全轉火","全轉木","全轉回復"]},
{"no":"2909","tag":["全轉水","全轉木","全轉回復"]},
{"no":"2910","tag":["木轉闇","光轉回復"]},
{"no":"2915","tag":["隨機轉火"]},
{"no":"2916","tag":["隨機轉火"]},
{"no":"2917","tag":["隨機轉水"]},
{"no":"2918","tag":["隨機轉水"]},
{"no":"2919","tag":["隨機轉木"]},
{"no":"2920","tag":["隨機轉木"]},
{"no":"2921","tag":["全轉火","全轉水","全轉木","全轉光"]},
{"no":"2922","tag":["全轉火","全轉水","全轉木","全轉光"]},
{"no":"2923","tag":["隨機轉闇"]},
{"no":"2924","tag":["隨機轉闇"]},
{"no":"2925","tag":["全轉光","全轉闇","全轉回復"]},
{"no":"2926","tag":["隨機轉火"]},
{"no":"2927","tag":["全轉火","全轉水","全轉木","全轉光","全轉闇"]},
{"no":"2930","tag":["横轉火"]},
{"no":"2931","tag":["横轉火"]},
{"no":"2932","tag":["横轉火"]},
{"no":"2933","tag":["横轉水"]},
{"no":"2934","tag":["横轉水"]},
{"no":"2935","tag":["横轉水"]},
{"no":"2936","tag":["横轉木"]},
{"no":"2937","tag":["横轉木"]},
{"no":"2938","tag":["横轉木"]},
{"no":"2939","tag":["横轉火","横轉木"]},
{"no":"2942","tag":["全轉火","全轉水","全轉木","全轉光","全轉暗","全轉回復"]},
{"no":"2943","tag":["全轉火","全轉水","全轉木","全轉光","全轉暗","全轉回復"]},
{"no":"2948","tag":["全轉木"]},
{"no":"2949","tag":["木轉光","回復轉光","邪魔轉光","毒轉光"]},
{"no":"2950","tag":["全轉火","全轉光","全轉闇","全轉回復"]},
{"no":"2951","tag":["水轉光","邪魔轉光","毒轉光"]},
{"no":"2954","tag":["火轉光","水轉回復"]},
{"no":"2955","tag":["火轉回復","闇轉回復","毒轉回復"]},
{"no":"2956","tag":["水轉回復","光轉回復","毒轉回復"]},
{"no":"2958","tag":["水轉回復"]},
{"no":"2960","tag":["水轉回復"]},
{"no":"2964","tag":["木轉光","回復轉光","邪魔轉光","毒轉光"]},
{"no":"2965","tag":["水轉光","邪魔轉光","毒轉光"]},
{"no":"2966","tag":["火轉光","水轉回復"]},
{"no":"2967","tag":["隨機轉回復"]},
{"no":"2968","tag":["隨機轉回復"]},
{"no":"2969","tag":["隨機轉回復"]},
{"no":"2970","tag":["隨機轉火","隨機轉光"]},
{"no":"2971","tag":["隨機轉水","隨機轉回復"]},
{"no":"2972","tag":["隨機轉木","隨機轉回復"]},
{"no":"2978","tag":["隨機轉火"]},
{"no":"2982","tag":["火轉水","回復轉闇","邪魔轉木","毒轉木"]},
{"no":"2990","tag":["隨機轉火","隨機轉回復"]},
{"no":"2991","tag":["隨機轉火","隨機轉回復"]},
{"no":"2992","tag":["火轉水","木轉水"]},
{"no":"2993","tag":["火轉水","木轉水"]},
{"no":"2994","tag":["邪魔轉木","毒轉木","隨機轉回復"]},
{"no":"2995","tag":["邪魔轉木","毒轉木","隨機轉回復"]},
{"no":"2996","tag":["隨機轉光","隨機轉回復"]},
{"no":"2997","tag":["隨機轉光","隨機轉回復"]},
{"no":"2998","tag":["隨機轉闇","隨機轉回復"]},
{"no":"2999","tag":["隨機轉闇","隨機轉回復"]},
{"no":"3000","tag":["隨機轉火","隨機轉光"]},
{"no":"3001","tag":["隨機轉水","隨機轉回復"]},
{"no":"3002","tag":["隨機轉木","隨機轉回復"]},
{"no":"3011","tag":["縦轉水"]},
{"no":"3012","tag":["隨機轉水","隨機轉光"]},
{"no":"3013","tag":["隨機轉水","隨機轉光"]},
{"no":"3014","tag":["水轉邪魔","毒轉邪魔"]},
{"no":"3015","tag":["水轉邪魔","毒轉邪魔"]},
{"no":"3016","tag":["水轉邪魔","毒轉邪魔"]},
{"no":"3017","tag":["水轉邪魔","毒轉邪魔"]},
{"no":"3018","tag":["隨機轉火","隨機轉光"]},
{"no":"3019","tag":["隨機轉火","隨機轉光"]},
{"no":"3020","tag":["横轉水","横轉光"]},
{"no":"3021","tag":["横轉水","横轉光"]},
{"no":"3022","tag":["縦轉光"]},
{"no":"3023","tag":["縦轉光"]},
{"no":"3026","tag":["闇轉回復","邪魔轉回復","毒轉回復"]},
{"no":"3027","tag":["闇轉回復","邪魔轉回復","毒轉回復"]},
{"no":"3028","tag":["隨機轉水"]},
{"no":"3029","tag":["隨機轉水"]},
{"no":"3030","tag":["光轉火","邪魔轉火"]},
{"no":"3031","tag":["光轉火","邪魔轉火"]},
{"no":"3032","tag":["隨機轉闇"]},
{"no":"3033","tag":["隨機轉闇"]},
{"no":"3034","tag":["隨機轉光"]},
{"no":"3035","tag":["隨機轉光"]},
{"no":"3040","tag":["光轉木","水轉闇","邪魔轉火"]},
{"no":"3041","tag":["光轉木","水轉闇","邪魔轉火"]},
{"no":"3042","tag":["隨機轉水","隨機轉闇","隨機轉邪魔"]},
{"no":"3043","tag":["隨機轉水","隨機轉闇","隨機轉邪魔"]},
{"no":"3048","tag":["隨機轉火","隨機轉光"]},
{"no":"3050","tag":["隨機轉水"]},
{"no":"3051","tag":["隨機轉闇"]},
{"no":"3052","tag":["隨機轉光"]},
{"no":"3053","tag":["回復轉火","邪魔轉火","毒轉火"]},
{"no":"3054","tag":["回復轉火","邪魔轉火","毒轉火"]},
{"no":"3055","tag":["回復轉水","邪魔轉水","毒轉水"]},
{"no":"3056","tag":["回復轉水","邪魔轉水","毒轉水"]},
{"no":"3057","tag":["回復轉木","邪魔轉木","毒轉木"]},
{"no":"3058","tag":["回復轉木","邪魔轉木","毒轉木"]},
{"no":"3059","tag":["回復轉光","邪魔轉光","毒轉光"]},
{"no":"3060","tag":["回復轉光","邪魔轉光","毒轉光"]},
{"no":"3061","tag":["回復轉闇","邪魔轉闇","毒轉闇"]},
{"no":"3062","tag":["回復轉闇","邪魔轉闇","毒轉闇"]},
{"no":"3063","tag":["全轉火","全轉闇"]},
{"no":"3064","tag":["全轉水","全轉闇"]},
{"no":"3065","tag":["全轉木","全轉闇"]},
{"no":"3068","tag":["隨機轉火"]},
{"no":"3069","tag":["隨機轉水"]},
{"no":"3070","tag":["隨機轉木"]},
{"no":"3075","tag":["回復轉水","邪魔轉水","毒轉水"]},
{"no":"3077","tag":["縦轉木"]},
{"no":"3078","tag":["縦轉木"]},
{"no":"3079","tag":["縦轉火"]},
{"no":"3080","tag":["縦轉火"]},
{"no":"3085","tag":["回復轉毒"]},
{"no":"3086","tag":["隨機轉光"]},
{"no":"3087","tag":["隨機轉光"]},
{"no":"3088","tag":["回復轉光"]},
{"no":"3090","tag":["全轉火","全轉水","全轉闇","全轉回復"]},
{"no":"3091","tag":["横轉火"]},
{"no":"3092","tag":["横轉水"]},
{"no":"3093","tag":["横轉木"]},
{"no":"3096","tag":["全轉水","全轉闇","全轉回復"]},
{"no":"3097","tag":["全轉木","全轉光","全轉回復"]},
{"no":"3098","tag":["全轉火","全轉光","全轉回復"]},
{"no":"3099","tag":["全轉火","全轉水","全轉木","全轉光","全轉闇"]},
{"no":"3101","tag":["水轉火","光轉回復"]},
{"no":"3102","tag":["水轉火","光轉回復"]},
{"no":"3103","tag":["全轉火","全轉水"]},
{"no":"3104","tag":["全轉火","全轉水"]},
{"no":"3105","tag":["全轉木","全轉闇","全轉回復"]},
{"no":"3106","tag":["全轉木","全轉闇","全轉回復"]},
{"no":"3109","tag":["火轉闇","水轉回復"]},
{"no":"3110","tag":["火轉闇","水轉回復"]},
{"no":"3112","tag":["隨機轉回復"]},
{"no":"3113","tag":["木轉水","回復轉水","邪魔轉水","毒轉水"]},
{"no":"3114","tag":["全轉水","全轉木","全轉光"]},
{"no":"3115","tag":["隨機轉回復"]},
{"no":"3116","tag":["木轉回復","闇轉回復","毒轉回復"]},
{"no":"3117","tag":["火轉回復","光轉回復","毒轉回復"]},
{"no":"3118","tag":["全轉火"]},
{"no":"3119","tag":["隨機轉木"]},
{"no":"3121","tag":["全轉水","全轉木","全轉光"]},
{"no":"3122","tag":["隨機轉回復"]},
{"no":"3123","tag":["木轉水","回復轉水","邪魔轉水","毒轉水"]},
{"no":"3124","tag":["木轉火","邪魔轉火","毒轉火"]},
{"no":"3125","tag":["木轉火","邪魔轉火","毒轉火"]},
{"no":"3126","tag":["闇轉木","毒轉木"]},
{"no":"3127","tag":["闇轉木","毒轉木"]},
{"no":"3128","tag":["火轉闇","木轉闇","邪魔轉闇","毒轉闇"]},
{"no":"3129","tag":["火轉闇","木轉闇","邪魔轉闇","毒轉闇"]},
{"no":"3134","tag":["横轉木"]},
{"no":"3135","tag":["横轉木"]},
{"no":"3138","tag":["邪魔轉水","毒轉水"]},
{"no":"3139","tag":["邪魔轉水","毒轉水"]},
{"no":"3144","tag":["隨機轉闇"]},
{"no":"3145","tag":["隨機轉闇"]},
{"no":"3148","tag":["木轉火","邪魔轉火","毒轉火"]},
{"no":"3149","tag":["闇轉木","毒轉木"]},
{"no":"3150","tag":["火轉闇","木轉闇","邪魔轉闇","毒轉闇"]},
{"no":"3151","tag":["全轉水","全轉木","全轉光"]},
{"no":"3154","tag":["邪魔轉回復","毒轉回復"]},
{"no":"3155","tag":["邪魔轉回復","毒轉回復"]},
{"no":"3156","tag":["邪魔轉回復","毒轉回復"]},
{"no":"3157","tag":["邪魔轉回復","毒轉回復"]},
{"no":"3165","tag":["横轉闇"]},
{"no":"3166","tag":["光轉火","回復轉火","邪魔轉火","毒轉火"]},
{"no":"3167","tag":["全轉火","全轉木","全轉回復"]},
{"no":"3168","tag":["闇轉火","回復轉木"]},
{"no":"3169","tag":["闇轉火","回復轉木"]},
{"no":"3170","tag":["闇轉火"]},
{"no":"3171","tag":["光轉火","回復轉火","邪魔轉火","毒轉火"]},
{"no":"3174","tag":["全轉光","全轉闇","全轉回復"]},
{"no":"3175","tag":["全轉光","全轉闇","全轉回復"]},
{"no":"3176","tag":["水轉光","闇轉回復"]},
{"no":"3177","tag":["火轉水","光轉回復"]},
{"no":"3178","tag":["水轉木","火轉回復"]},
{"no":"3179","tag":["木轉火","闇轉回復"]},
{"no":"3180","tag":["光轉木","闇轉回復"]},
{"no":"3181","tag":["木轉闇","光轉回復"]},
{"no":"3192","tag":["隨機轉光","隨機轉回復"]},
{"no":"3194","tag":["隨機轉火","隨機轉回復"]},
{"no":"3196","tag":["全轉火","全轉木","全轉回復"]},
{"no":"3199","tag":["火轉水","回復轉水"]},
{"no":"3200","tag":["火轉水","回復轉水"]},
{"no":"3208","tag":["火轉水","回復轉水"]},
{"no":"3213","tag":["闇轉水","回復轉水"]},
{"no":"3216","tag":["木轉回復"]},
{"no":"3222","tag":["隨機轉回復"]},
{"no":"3224","tag":["全轉水","全轉木","全轉闇"]},
{"no":"3225","tag":["光轉回復"]},
{"no":"3226","tag":["木轉闇"]},
{"no":"3227","tag":["水轉回復"]},
{"no":"3230","tag":["横轉毒"]},
{"no":"3231","tag":["隨機轉回復"]},
{"no":"3232","tag":["木轉闇"]},
{"no":"3235","tag":["全轉火","全轉光"]},
{"no":"3236","tag":["全轉火","全轉光"]},
{"no":"3238","tag":["闇轉火"]},
{"no":"3242","tag":["隨機轉回復"]},
{"no":"3243","tag":["水轉回復"]},
{"no":"3246","tag":["全轉火","全轉水","全轉木","全轉光","全轉闇"]},
{"no":"3249","tag":["全轉水","全轉木","全轉闇"]},
{"no":"3252","tag":["隨機轉闇"]},
{"no":"3253","tag":["回復轉光","闇轉回復"]},
{"no":"3254","tag":["回復轉光","邪魔轉光"]},
{"no":"3256","tag":["縦轉木","縦轉光"]},
{"no":"3257","tag":["隨機轉光"]},
{"no":"3260","tag":["隨機轉火","隨機轉光"]},
{"no":"3266","tag":["隨機轉闇","隨機轉回復"]},
{"no":"3267","tag":["全轉火","全轉水","全轉木","全轉光","全轉暗","全轉回復","全轉邪魔"]},
{"no":"3268","tag":["全轉火","全轉水","全轉木","全轉光","全轉暗","全轉回復","全轉邪魔"]},
{"no":"3271","tag":["水轉火","回復轉闇"]},
{"no":"3274","tag":["全轉火","全轉光"]},
{"no":"3275","tag":["木轉火","回復轉火","邪魔轉火","毒轉火"]},
{"no":"3276","tag":["闇轉水","回復轉水"]},
{"no":"3277","tag":["全轉火","全轉木","全轉闇"]},
{"no":"3278","tag":["全轉火","全轉水","全轉木","全轉光","全轉闇"]},
{"no":"3279","tag":["全轉火","全轉闇"]},
{"no":"3280","tag":["木轉火","光轉火"]},
{"no":"3281","tag":["縦轉回復"]},
{"no":"3283","tag":["全轉木","全轉光","全轉回復"]},
{"no":"3284","tag":["全轉光","全轉闇"]},
{"no":"3285","tag":["光轉闇"]},
{"no":"3286","tag":["全轉火","全轉光"]},
{"no":"3287","tag":["縦轉回復"]},
{"no":"3288","tag":["闇轉水","回復轉水"]},
{"no":"3289","tag":["木轉火","光轉火"]},
{"no":"3290","tag":["全轉木","全轉光","全轉回復"]},
{"no":"3291","tag":["全轉光","全轉闇"]},
{"no":"3292","tag":["木轉火","回復轉火","邪魔轉火","毒轉火"]},
{"no":"3293","tag":["全轉火","全轉闇"]},
{"no":"3294","tag":["闇轉水","火轉回復"]},
{"no":"3295","tag":["木轉火","闇轉光"]},
{"no":"3296","tag":["木轉火","闇轉光"]},
{"no":"3297","tag":["回復轉光"]},
{"no":"3298","tag":["回復轉光"]},
{"no":"3299","tag":["回復轉光"]},
{"no":"3300","tag":["隨機轉火","隨機轉闇"]},
{"no":"3301","tag":["隨機轉火","隨機轉闇"]},
{"no":"3302","tag":["闇轉回復","邪魔轉回復","毒轉回復"]},
{"no":"3303","tag":["闇轉回復","邪魔轉回復","毒轉回復"]},
{"no":"3304","tag":["隨機轉闇"]},
{"no":"3305","tag":["隨機轉闇"]},
{"no":"3307","tag":["木轉火","闇轉光"]},
{"no":"3308","tag":["回復轉光"]},
{"no":"3309","tag":["隨機轉闇"]},
{"no":"3328","tag":["光轉木"]},
{"no":"3329","tag":["光轉木"]},
{"no":"3330","tag":["全轉火","全轉闇","全轉回復"]},
{"no":"3331","tag":["隨機轉火","隨機轉回復"]},
{"no":"3332","tag":["隨機轉火","隨機轉回復"]},
{"no":"3333","tag":["全轉火","全轉水","全轉木","全轉光","全轉暗","全轉回復","全轉邪魔"]},
{"no":"3334","tag":["全轉火","全轉水","全轉木","全轉光","全轉暗","全轉回復","全轉邪魔"]},
{"no":"3335","tag":["全轉火","全轉木","全轉光"]},
{"no":"3336","tag":["全轉火","全轉木","全轉光"]},
{"no":"3337","tag":["隨機轉火"]},
{"no":"3338","tag":["隨機轉火"]},
{"no":"3339","tag":["木轉水"]},
{"no":"3340","tag":["木轉水"]},
{"no":"3341","tag":["横轉木"]},
{"no":"3342","tag":["横轉木"]},
{"no":"3343","tag":["光轉火","水轉闇"]},
{"no":"3344","tag":["光轉火","水轉闇"]},
{"no":"3345","tag":["闇轉水","木轉火"]},
{"no":"3346","tag":["闇轉水","木轉火"]},
{"no":"3347","tag":["闇轉木","火轉光"]},
{"no":"3348","tag":["闇轉木","火轉光"]},
{"no":"3351","tag":["火轉闇","光轉水"]},
{"no":"3352","tag":["火轉闇","光轉水"]},
{"no":"3354","tag":["全轉火","全轉水","全轉木","全轉光","全轉暗","全轉回復"]},
{"no":"3355","tag":["縦轉水"]},
{"no":"3356","tag":["水轉火","回復轉火"]},
{"no":"3357","tag":["水轉火","回復轉火"]},
{"no":"3358","tag":["木轉闇","火轉回復"]},
{"no":"3359","tag":["木轉闇","火轉回復"]},
{"no":"3366","tag":["水轉火","回復轉火"]},
{"no":"3367","tag":["木轉闇","火轉回復"]},
{"no":"3374","tag":["全轉火","全轉水","全轉闇"]},
{"no":"3375","tag":["闇轉火","回復轉火"]},
{"no":"3377","tag":["木轉火"]},
{"no":"3378","tag":["縦轉光","縦轉闇"]},
{"no":"3379","tag":["隨機轉火","隨機轉回復"]},
{"no":"3380","tag":["縦轉光","縦轉闇"]},
{"no":"3381","tag":["木轉火"]},
{"no":"3382","tag":["隨機轉火","隨機轉回復"]},
{"no":"3385","tag":["木轉闇","邪魔轉闇","毒轉闇"]},
{"no":"3393","tag":["隨機轉回復"]},
{"no":"3394","tag":["全轉火","全轉水","全轉木","全轉光","全轉暗","全轉回復"]},
{"no":"3395","tag":["全轉火","全轉木","全轉光"]},
{"no":"3396","tag":["木轉火","闇轉回復"]},
{"no":"3397","tag":["木轉水","回復轉闇"]},
{"no":"3399","tag":["横轉闇"]},
{"no":"3400","tag":["横轉闇"]},
{"no":"3401","tag":["隨機轉回復"]},
{"no":"3402","tag":["全轉火","全轉水","全轉木","全轉光","全轉暗","全轉回復"]},
{"no":"3403","tag":["全轉火","全轉木","全轉光"]},
{"no":"3404","tag":["木轉火","闇轉回復"]},
{"no":"3405","tag":["木轉水","回復轉闇"]},
{"no":"3408","tag":["縦轉闇"]},
{"no":"3409","tag":["縦轉闇"]},
{"no":"3412","tag":["縦轉闇"]},
{"no":"3417","tag":["全轉火","全轉木","全轉光"]},
{"no":"3419","tag":["縦轉光","縦轉木"]},
{"no":"3421","tag":["縦轉光","縦轉木"]},
{"no":"3422","tag":["隨機轉回復"]},
{"no":"3423","tag":["隨機轉木","隨機轉光"]},
{"no":"3424","tag":["隨機轉木","隨機轉光"]},
{"no":"3425","tag":["隨機轉木","隨機轉回復"]},
{"no":"3426","tag":["隨機轉木","隨機轉光"]},
{"no":"3427","tag":["隨機轉木","隨機轉回復"]},
{"no":"3429","tag":["回復轉光","邪魔轉光","毒轉光"]},
{"no":"3430","tag":["隨機轉火"]},
{"no":"3431","tag":["全轉水","全轉光","全轉闇","全轉回復"]},
{"no":"3432","tag":["全轉水","全轉木","全轉光"]},
{"no":"3435","tag":["隨機轉火","隨機轉水"]},
{"no":"3436","tag":["隨機轉火","隨機轉水"]},
{"no":"3437","tag":["隨機轉火","隨機轉水"]},
{"no":"3438","tag":["回復轉光"]},
{"no":"3439","tag":["回復轉光"]},
{"no":"3440","tag":["横轉火"]},
{"no":"3441","tag":["横轉火"]},
{"no":"3442","tag":["隨機轉回復"]},
{"no":"3443","tag":["隨機轉回復"]},
{"no":"3445","tag":["隨機轉火","隨機轉水"]},
{"no":"3446","tag":["横轉火"]},
{"no":"3447","tag":["隨機轉火","隨機轉回復"]},
{"no":"3451","tag":["回復轉火"]},
{"no":"3452","tag":["縦轉水"]},
{"no":"3453","tag":["縦轉木"]},
{"no":"3460","tag":["回復轉火","邪魔轉火","毒轉火"]},
{"no":"3461","tag":["隨機轉火","隨機轉回復"]},
{"no":"3462","tag":["縦轉火","縦轉回復"]},
{"no":"3463","tag":["縦轉火","縦轉回復"]},
{"no":"3464","tag":["横轉火"]},
{"no":"3465","tag":["横轉火"]},
{"no":"3466","tag":["隨機轉闇"]},
{"no":"3467","tag":["隨機轉闇"]},
{"no":"3470","tag":["隨機轉闇","隨機轉火"]},
{"no":"3471","tag":["隨機轉闇","隨機轉火"]},
{"no":"3472","tag":["闇轉火","邪魔轉火"]},
{"no":"3473","tag":["闇轉火","邪魔轉火"]},
{"no":"3474","tag":["闇轉火","水轉光"]},
{"no":"3475","tag":["闇轉火","水轉光"]},
{"no":"3477","tag":["縦轉火","縦轉回復"]},
{"no":"3478","tag":["横轉火"]},
{"no":"3479","tag":["隨機轉闇"]},
{"no":"3481","tag":["隨機轉闇","隨機轉火"]},
{"no":"3487","tag":["全轉火","全轉木","全轉光"]},
{"no":"3488","tag":["全轉水","全轉木","全轉闇"]},
{"no":"3489","tag":["全轉木","全轉光","全轉闇"]},
{"no":"3491","tag":["全轉火","全轉水","全轉闇"]},
{"no":"3492","tag":["水轉火","回復轉火"]},
{"no":"3493","tag":["木轉水","回復轉水"]},
{"no":"3494","tag":["火轉木","回復轉木"]},
{"no":"3495","tag":["闇轉光","回復轉光"]},
{"no":"3496","tag":["光轉闇","回復轉闇"]},
{"no":"3497","tag":["水轉火","毒轉火"]},
{"no":"3499","tag":["闇轉木","回復轉木"]},
{"no":"3500","tag":["闇轉光","火轉回復","邪魔轉水","毒轉水"]},
{"no":"3502","tag":["火轉水","回復轉闇","邪魔轉木","毒轉木"]},
{"no":"3506","tag":["木轉闇","光轉回復"]},
{"no":"3507","tag":["火轉木","邪魔轉木","毒轉木"]},
{"no":"3508","tag":["隨機轉闇"]},
{"no":"3509","tag":["木轉火","闇轉回復","邪魔轉水","毒轉水"]},
{"no":"3510","tag":["火轉水","光轉回復","邪魔轉木","毒轉木"]},
{"no":"3511","tag":["水轉木","火轉回復","邪魔轉闇","毒轉闇"]},
{"no":"3512","tag":["水轉光","闇轉回復"]},
{"no":"3513","tag":["全轉火","全轉光"]},
{"no":"3514","tag":["木轉火","回復轉火","邪魔轉火","毒轉火"]},
{"no":"3515","tag":["闇轉水","回復轉水"]},
{"no":"3516","tag":["全轉火","全轉木","全轉闇"]},
{"no":"3517","tag":["全轉火","全轉水","全轉木","全轉光","全轉闇"]},
{"no":"3518","tag":["全轉火","全轉闇"]},
{"no":"3519","tag":["木轉火","光轉火"]},
{"no":"3520","tag":["縦轉回復"]},
{"no":"3522","tag":["全轉木","全轉光","全轉回復"]},
{"no":"3523","tag":["全轉光","全轉闇"]},
{"no":"3524","tag":["全轉火","全轉水","全轉木","全轉光","全轉暗","全轉回復"]},
{"no":"3525","tag":["全轉火","全轉水","全轉木","全轉光","全轉暗","全轉回復"]},
{"no":"3531","tag":["木轉火","邪魔轉火","毒轉火"]},
{"no":"3532","tag":["火轉水","邪魔轉水","毒轉水"]},
{"no":"3533","tag":["水轉光","邪魔轉光","毒轉光"]},
{"no":"3536","tag":["隨機轉光"]},
{"no":"3537","tag":["隨機轉闇"]},
{"no":"3548","tag":["水轉光","闇轉回復"]},
{"no":"3549","tag":["火轉光","闇轉回復"]},
{"no":"3550","tag":["水轉光","火轉回復"]},
{"no":"3551","tag":["水轉闇","木轉回復"]},
{"no":"3552","tag":["火轉木","光轉回復"]},
{"no":"3554","tag":["隨機轉闇"]},
{"no":"3557","tag":["火轉闇","邪魔轉闇","毒轉闇"]},
{"no":"3558","tag":["火轉闇","邪魔轉闇","毒轉闇"]},
{"no":"3559","tag":["隨機轉回復"]},
{"no":"3560","tag":["隨機轉回復"]},
{"no":"3561","tag":["隨機轉闇"]},
{"no":"3562","tag":["隨機轉闇"]},
{"no":"3564","tag":["火轉闇","邪魔轉闇","毒轉闇"]},
{"no":"3565","tag":["隨機轉木","隨機轉回復"]},
{"no":"3566","tag":["全轉火","全轉木","全轉光"]},
{"no":"3569","tag":["光轉回復"]},
{"no":"3570","tag":["全轉水","全轉木","全轉光","全轉闇"]},
{"no":"3571","tag":["隨機轉木","隨機轉闇"]},
{"no":"3572","tag":["隨機轉光"]},
{"no":"3573","tag":["全轉火","全轉水","全轉木","全轉闇"]},
{"no":"3576","tag":["光轉木","水轉毒"]},
{"no":"3577","tag":["隨機轉光"]},
{"no":"3578","tag":["木轉回復"]},
{"no":"3580","tag":["水轉闇","邪魔轉闇","毒轉闇"]},
{"no":"3581","tag":["水轉闇","邪魔轉闇","毒轉闇"]},
{"no":"3582","tag":["隨機轉火","隨機轉邪魔"]},
{"no":"3583","tag":["隨機轉火","隨機轉邪魔"]},
{"no":"3584","tag":["隨機轉水","隨機轉邪魔"]},
{"no":"3585","tag":["隨機轉水","隨機轉邪魔"]},
{"no":"3586","tag":["隨機轉木","隨機轉邪魔"]},
{"no":"3587","tag":["隨機轉木","隨機轉邪魔"]},
{"no":"3588","tag":["闇轉光","回復轉光","毒轉光"]},
{"no":"3589","tag":["闇轉光","回復轉光","毒轉光"]},
{"no":"3590","tag":["光轉闇","回復轉闇","毒轉闇"]},
{"no":"3591","tag":["光轉闇","回復轉闇","毒轉闇"]},
{"no":"3592","tag":["縦轉火"]},
{"no":"3593","tag":["縦轉水"]},
{"no":"3594","tag":["縦轉木"]},
{"no":"3597","tag":["隨機轉闇"]},
{"no":"3598","tag":["隨機轉闇"]},
{"no":"3602","tag":["全轉水","全轉光","全轉回復"]},
{"no":"3603","tag":["全轉水","全轉光","全轉回復"]},
{"no":"3604","tag":["全轉火","全轉闇"]},
{"no":"3605","tag":["隨機轉火"]},
{"no":"3606","tag":["隨機轉火"]},
{"no":"3607","tag":["全轉火","全轉水","全轉木","全轉光","全轉闇"]},
{"no":"3608","tag":["全轉火","全轉水","全轉闇","全轉回復"]},
{"no":"3609","tag":["全轉火","全轉水","全轉闇","全轉回復"]},
{"no":"3614","tag":["火轉木","闇轉回復"]},
{"no":"3615","tag":["火轉木","闇轉回復"]},
{"no":"3616","tag":["縦轉水","縦轉木"]},
{"no":"3617","tag":["全轉火","全轉水","全轉木","全轉光","全轉暗","全轉回復"]},
{"no":"3618","tag":["全轉火","全轉水","全轉木","全轉光","全轉暗","全轉回復"]},
{"no":"3619","tag":["闇轉木","邪魔轉木"]},
{"no":"3622","tag":["光轉闇"]},
{"no":"3623","tag":["光轉闇"]},
{"no":"3628","tag":["全轉水","全轉闇","全轉邪魔"]},
{"no":"3629","tag":["全轉水","全轉闇","全轉邪魔"]},
{"no":"3632","tag":["隨機轉火"]},
{"no":"3633","tag":["全轉火","全轉水","全轉闇","全轉回復"]},
{"no":"3635","tag":["火轉木","闇轉回復"]},
{"no":"3636","tag":["全轉火","全轉水","全轉木","全轉光","全轉暗","全轉回復"]},
{"no":"3637","tag":["回復轉水","邪魔轉水","毒轉水"]},
{"no":"3638","tag":["回復轉水","邪魔轉水","毒轉水"]},
{"no":"3639","tag":["回復轉木","邪魔轉木","毒轉木"]},
{"no":"3640","tag":["回復轉木","邪魔轉木","毒轉木"]},
{"no":"3641","tag":["全轉火","全轉水","全轉木","全轉光","全轉暗","全轉回復"]},
{"no":"3642","tag":["全轉火","全轉水","全轉木","全轉光","全轉暗","全轉回復"]},
{"no":"3645","tag":["全轉光","全轉回復"]},
{"no":"3646","tag":["全轉光","全轉回復"]},
{"no":"3647","tag":["全轉火","全轉水","全轉木","全轉光","全轉暗","全轉回復"]},
{"no":"3652","tag":["隨機轉火"]},
{"no":"3654","tag":["横轉光"]},
{"no":"3655","tag":["全轉火","全轉木","全轉邪魔"]},
{"no":"3656","tag":["縦轉闇"]},
{"no":"3657","tag":["闇轉水","木轉回復"]},
{"no":"3658","tag":["縦轉火"]},
{"no":"3659","tag":["隨機轉水","隨機轉木","隨機轉闇"]},
{"no":"3662","tag":["全轉火","全轉水","全轉木","全轉光","全轉闇"]},
{"no":"3664","tag":["横轉火"]},
{"no":"3665","tag":["横轉火"]},
{"no":"3666","tag":["隨機轉火"]},
{"no":"3670","tag":["横轉光"]},
{"no":"3671","tag":["全轉火","全轉木","全轉邪魔"]},
{"no":"3672","tag":["隨機轉闇"]},
{"no":"3673","tag":["隨機轉闇"]},
{"no":"3674","tag":["縦轉闇"]},
{"no":"3675","tag":["闇轉水","木轉回復"]},
{"no":"3678","tag":["縦轉火"]},
{"no":"3679","tag":["隨機轉水","隨機轉木","隨機轉闇"]},
{"no":"3684","tag":["全轉火","全轉水","全轉木","全轉光","全轉闇"]},
{"no":"3688","tag":["光轉水","回復轉水","邪魔轉水","毒轉水"]},
{"no":"3689","tag":["光轉水","回復轉水","邪魔轉水","毒轉水"]},
{"no":"3690","tag":["全轉火","全轉木","全轉回復"]},
{"no":"3691","tag":["全轉火","全轉木","全轉回復"]},
{"no":"3692","tag":["全轉水","全轉光","全轉回復"]},
{"no":"3693","tag":["全轉水","全轉光","全轉回復"]},
{"no":"3694","tag":["全轉木","全轉闇","全轉回復"]},
{"no":"3695","tag":["全轉木","全轉闇","全轉回復"]},
{"no":"3696","tag":["全轉火","全轉水","全轉木","全轉光","全轉回復"]},
{"no":"3697","tag":["全轉火","全轉水","全轉木","全轉光","全轉回復"]},
{"no":"3698","tag":["全轉火","全轉水","全轉木","全轉闇","全轉回復"]},
{"no":"3699","tag":["全轉火","全轉水","全轉木","全轉闇","全轉回復"]},
{"no":"3705","tag":["横轉火"]},
{"no":"3710","tag":["隨機轉闇"]},
{"no":"3712","tag":["光轉火","闇轉回復"]},
{"no":"3713","tag":["光轉水","闇轉回復"]},
{"no":"3714","tag":["光轉木","闇轉回復"]},
{"no":"3716","tag":["縦轉闇","縦轉回復"]},
{"no":"3721","tag":["光轉火","水轉闇"]},
{"no":"3722","tag":["闇轉水","木轉火"]},
{"no":"3723","tag":["闇轉木","火轉光"]},
{"no":"3725","tag":["火轉闇","光轉水"]},
{"no":"3726","tag":["水轉光","闇轉回復"]},
{"no":"3727","tag":["火轉光","闇轉回復"]},
{"no":"3728","tag":["水轉光","火轉回復"]},
{"no":"3729","tag":["水轉闇","木轉回復"]},
{"no":"3730","tag":["火轉木","光轉回復"]},
{"no":"3733","tag":["全轉火"]},
{"no":"3734","tag":["全轉火"]},
{"no":"3735","tag":["隨機轉水"]},
{"no":"3736","tag":["隨機轉水"]},
{"no":"3737","tag":["横轉水"]},
{"no":"3738","tag":["横轉水"]},
{"no":"3739","tag":["縦轉水"]},
{"no":"3740","tag":["縦轉水"]},
{"no":"3741","tag":["全轉火","全轉闇","全轉回復"]},
{"no":"3742","tag":["全轉水","全轉闇","全轉回復"]},
{"no":"3743","tag":["全轉木","全轉闇","全轉回復"]},
{"no":"3744","tag":["全轉光","全轉闇","全轉回復"]},
{"no":"3745","tag":["全轉闇","全轉回復","全轉邪魔"]},
{"no":"3746","tag":["全轉火","全轉木","全轉光","全轉回復"]},
{"no":"3747","tag":["全轉火","全轉木","全轉光","全轉回復"]},
{"no":"3748","tag":["全轉水","全轉木","全轉闇","全轉回復"]},
{"no":"3749","tag":["全轉水","全轉木","全轉闇","全轉回復"]},
{"no":"3750","tag":["全轉木","全轉光","全轉闇","全轉回復"]},
{"no":"3751","tag":["全轉木","全轉光","全轉闇","全轉回復"]},
{"no":"3752","tag":["全轉火","全轉水","全轉光","全轉回復"]},
{"no":"3753","tag":["全轉火","全轉水","全轉光","全轉回復"]},
{"no":"3754","tag":["全轉火","全轉水","全轉闇","全轉回復"]},
{"no":"3755","tag":["全轉火","全轉水","全轉闇","全轉回復"]},
{"no":"3756","tag":["全轉火","全轉水","全轉木","全轉光","全轉暗","全轉回復"]},
{"no":"3757","tag":["全轉火","全轉闇","全轉回復"]},
{"no":"3758","tag":["全轉水","全轉闇","全轉回復"]},
{"no":"3759","tag":["全轉木","全轉闇","全轉回復"]},
{"no":"3760","tag":["全轉光","全轉闇","全轉回復"]},
{"no":"3761","tag":["全轉闇","全轉回復","全轉邪魔"]},
{"no":"3762","tag":["全轉火","全轉水","全轉回復"]},
{"no":"3763","tag":["全轉火","全轉木","全轉回復"]},
{"no":"3764","tag":["全轉水","全轉木","全轉回復"]},
{"no":"3765","tag":["全轉火","全轉闇"]},
{"no":"3766","tag":["全轉木","全轉闇"]},
{"no":"3767","tag":["全轉水","全轉闇"]},
{"no":"3768","tag":["全轉水","全轉闇","全轉回復"]},
{"no":"3769","tag":["全轉水","全轉闇","全轉回復"]},
{"no":"3770","tag":["全轉木","全轉光","全轉回復"]},
{"no":"3771","tag":["全轉木","全轉光","全轉回復"]},
{"no":"3772","tag":["全轉火","全轉光","全轉回復"]},
{"no":"3773","tag":["全轉火","全轉光","全轉回復"]},
{"no":"3775","tag":["全轉火","全轉水","全轉光","全轉闇","全轉回復"]},
{"no":"3776","tag":["横轉光"]},
{"no":"3777","tag":["横轉光"]},
{"no":"3780","tag":["横轉光"]},
{"no":"3782","tag":["隨機轉水","隨機轉木"]},
{"no":"3787","tag":["全轉火","全轉木","全轉闇"]},
{"no":"3788","tag":["全轉火","全轉水","全轉木","全轉光","全轉暗","全轉回復"]},
{"no":"3789","tag":["木轉光","回復轉光","邪魔轉光","毒轉光"]},
{"no":"3790","tag":["縦轉光","縦轉回復"]},
{"no":"3791","tag":["火轉闇","回復轉闇"]},
{"no":"3792","tag":["火轉闇","回復轉闇"]},
{"no":"3793","tag":["縦轉光","縦轉回復"]},
{"no":"3796","tag":["火轉木","毒轉木"]},
{"no":"3797","tag":["火轉木","毒轉木"]},
{"no":"3798","tag":["回復轉火","邪魔轉火"]},
{"no":"3799","tag":["回復轉火","邪魔轉火"]},
{"no":"3800","tag":["木轉水","邪魔轉水"]},
{"no":"3801","tag":["木轉水","邪魔轉水"]},
{"no":"3802","tag":["回復轉光","火轉闇"]},
{"no":"3803","tag":["回復轉光","火轉闇"]},
{"no":"3805","tag":["火轉木","毒轉木"]},
{"no":"3806","tag":["回復轉火","邪魔轉火"]},
{"no":"3807","tag":["木轉水","邪魔轉水"]},
{"no":"3808","tag":["縦轉光"]},
{"no":"3809","tag":["縦轉闇"]},
{"no":"3810","tag":["回復轉火","邪魔轉火"]},
{"no":"3811","tag":["回復轉水","邪魔轉水"]},
{"no":"3812","tag":["水轉木","闇轉光"]},
{"no":"3813","tag":["火轉水","闇轉光"]},
{"no":"3814","tag":["火轉光","回復轉光","邪魔轉光","毒轉光"]},
{"no":"3815","tag":["全轉光","全轉闇","全轉回復"]},
{"no":"3816","tag":["全轉光","全轉闇","全轉回復"]},
{"no":"3817","tag":["縦轉木"]},
{"no":"3818","tag":["縦轉火","縦轉光"]},
{"no":"3819","tag":["横轉闇","横轉木"]},
{"no":"3820","tag":["横轉光","横轉火"]},
{"no":"3821","tag":["横轉光"]},
{"no":"3822","tag":["闇轉水","火轉回復"]},
{"no":"3823","tag":["木轉火","闇轉光"]},
{"no":"3824","tag":["回復轉光"]},
{"no":"3825","tag":["火轉闇","水轉闇","木轉闇"]},
{"no":"3826","tag":["全轉火","全轉水","全轉木","全轉光","全轉暗","全轉回復","全轉邪魔"]},
{"no":"3835","tag":["全轉火","全轉木","全轉回復"]},
{"no":"3836","tag":["全轉水","全轉光","全轉回復"]},
{"no":"3837","tag":["全轉木","全轉闇","全轉回復"]},
{"no":"3838","tag":["全轉火","全轉水","全轉木","全轉光","全轉回復"]},
{"no":"3839","tag":["全轉火","全轉水","全轉木","全轉闇","全轉回復"]},
{"no":"3840","tag":["水轉火","光轉回復"]},
{"no":"3841","tag":["全轉火","全轉水"]},
{"no":"3842","tag":["全轉木","全轉闇","全轉回復"]},
{"no":"3844","tag":["火轉闇","水轉回復"]},
{"no":"3845","tag":["木轉水","回復轉水","邪魔轉水","毒轉水"]},
{"no":"3847","tag":["全轉火","全轉水","全轉木","全轉光","全轉回復"]},
{"no":"3848","tag":["火轉水","回復轉水"]},
{"no":"3849","tag":["火轉水","回復轉水"]},
{"no":"3850","tag":["木轉火","邪魔轉火","毒轉火"]},
{"no":"3851","tag":["光轉火","水轉木"]},
{"no":"3852","tag":["光轉火","水轉木"]},
{"no":"3853","tag":["光轉闇","木轉火"]},
{"no":"3854","tag":["光轉闇","木轉火"]},
{"no":"3855","tag":["火轉光","闇轉光"]},
{"no":"3856","tag":["火轉光","闇轉光"]},
{"no":"3857","tag":["闇轉火"]},
{"no":"3858","tag":["闇轉火"]},
{"no":"3860","tag":["邪魔轉水","毒轉水"]},
{"no":"3861","tag":["光轉火","水轉木"]},
{"no":"3862","tag":["光轉闇","木轉火"]},
{"no":"3868","tag":["火轉回復"]},
{"no":"3872","tag":["隨機轉闇","隨機轉邪魔"]},
{"no":"3873","tag":["隨機轉闇","隨機轉邪魔"]},
{"no":"3874","tag":["火轉邪魔","回復轉邪魔"]},
{"no":"3875","tag":["火轉邪魔","回復轉邪魔"]},
{"no":"3876","tag":["隨機轉光","隨機轉回復"]},
{"no":"3877","tag":["隨機轉光","隨機轉回復"]},
{"no":"3878","tag":["隨機轉闇","隨機轉回復"]},
{"no":"3879","tag":["隨機轉闇","隨機轉回復"]},
{"no":"3882","tag":["縦轉光"]},
{"no":"3883","tag":["縦轉光"]},
{"no":"3886","tag":["回復轉闇","邪魔轉闇","毒轉闇"]},
{"no":"3887","tag":["回復轉闇","邪魔轉闇","毒轉闇"]},
{"no":"3888","tag":["縦轉光"]},
{"no":"3890","tag":["回復轉闇","邪魔轉闇","毒轉闇"]},
{"no":"3892","tag":["全轉火","全轉水","全轉木","全轉光","全轉闇"]},
{"no":"3893","tag":["全轉火","全轉水","全轉木","全轉光","全轉闇"]},
{"no":"3894","tag":["全轉火","全轉水","全轉木","全轉光","全轉暗","全轉回復"]},
{"no":"3895","tag":["全轉火","全轉水","全轉木","全轉光","全轉暗","全轉回復"]},
{"no":"3896","tag":["闇轉回復","邪魔轉回復","毒轉回復"]},
{"no":"3897","tag":["水轉火","木轉回復"]},
{"no":"3898","tag":["木轉水","火轉回復"]},
{"no":"3899","tag":["火轉木","水轉回復"]},
{"no":"3900","tag":["火轉光","闇轉回復"]},
{"no":"3901","tag":["木轉闇","光轉回復"]},
{"no":"3905","tag":["全轉水"]},
{"no":"3907","tag":["全轉火","全轉光","全轉闇","全轉回復"]},
{"no":"3908","tag":["全轉火","全轉水","全轉闇","全轉回復"]},
{"no":"3910","tag":["全轉火","全轉光","全轉回復"]},
{"no":"3911","tag":["全轉火","全轉水","全轉木","全轉光","全轉暗","全轉回復"]},
{"no":"3912","tag":["全轉火","全轉闇"]},
{"no":"3913","tag":["隨機轉水","隨機轉回復"]},
{"no":"3916","tag":["全轉火","全轉木","全轉闇"]},
{"no":"3917","tag":["回復轉火"]},
{"no":"3918","tag":["回復轉水"]},
{"no":"3919","tag":["回復轉木"]},
{"no":"3920","tag":["回復轉光"]},
{"no":"3921","tag":["回復轉闇"]},
{"no":"3922","tag":["光轉火"]},
{"no":"3923","tag":["闇轉水"]},
{"no":"3924","tag":["水轉木"]},
{"no":"3925","tag":["木轉光"]},
{"no":"3926","tag":["火轉闇"]},
{"no":"3929","tag":["光轉水","回復轉木"]},
{"no":"3930","tag":["全轉火","全轉水","全轉木","全轉光","全轉暗","全轉回復"]},
{"no":"3931","tag":["全轉火","全轉水","全轉木","全轉光","全轉暗","全轉回復"]},
{"no":"3932","tag":["水轉火","闇轉火","邪魔轉回復","毒轉回復"]},
{"no":"3933","tag":["水轉火","闇轉火","邪魔轉回復","毒轉回復"]},
{"no":"3934","tag":["全轉火","全轉水","全轉回復"]},
{"no":"3935","tag":["全轉火","全轉水","全轉回復"]},
{"no":"3936","tag":["闇轉木","邪魔轉木","毒轉木"]},
{"no":"3937","tag":["闇轉木","邪魔轉木","毒轉木"]},
{"no":"3938","tag":["縦轉光","縦轉火"]},
{"no":"3939","tag":["縦轉光","縦轉火"]},
{"no":"3940","tag":["火轉闇","水轉木"]},
{"no":"3941","tag":["火轉闇","水轉木"]},
{"no":"3942","tag":["隨機轉火"]},
{"no":"3943","tag":["隨機轉火"]},
{"no":"3950","tag":["縦轉水","縦轉闇"]},
{"no":"3951","tag":["縦轉水","縦轉闇"]},
{"no":"3952","tag":["全轉火","全轉水","全轉木","全轉光","全轉暗","全轉回復"]},
{"no":"3953","tag":["全轉火","全轉水","全轉木","全轉光","全轉暗","全轉回復"]},
{"no":"3956","tag":["水轉火","闇轉火","邪魔轉回復","毒轉回復"]},
{"no":"3957","tag":["全轉火","全轉水","全轉回復"]},
{"no":"3958","tag":["闇轉木","邪魔轉木","毒轉木"]},
{"no":"3959","tag":["縦轉光","縦轉火"]},
{"no":"3960","tag":["火轉闇","水轉木"]},
{"no":"3961","tag":["隨機轉火"]},
{"no":"3965","tag":["縦轉水","縦轉闇"]},
{"no":"3971","tag":["火轉邪魔","回復轉邪魔"]},
{"no":"3975","tag":["邪魔轉木","毒轉木","隨機轉回復"]},
{"no":"3976","tag":["邪魔轉木","毒轉木","隨機轉回復"]},
{"no":"3979","tag":["全轉火","全轉水","全轉光"]},
{"no":"3981","tag":["縦轉闇"]},
{"no":"3982","tag":["水轉火","回復轉火"]},
{"no":"3983","tag":["火轉木","回復轉木"]},
{"no":"3985","tag":["全轉火","全轉水","全轉光"]},
{"no":"3987","tag":["縦轉火"]},
{"no":"3988","tag":["隨機轉闇"]},
{"no":"3991","tag":["隨機轉闇"]},
{"no":"3994","tag":["全轉木","全轉闇","全轉回復"]},
{"no":"3995","tag":["全轉水","全轉闇","全轉回復"]},
{"no":"3996","tag":["隨機轉木","隨機轉闇"]},
{"no":"3997","tag":["全轉木","全轉闇","全轉回復"]},
{"no":"3998","tag":["全轉水","全轉闇","全轉回復"]},
{"no":"4002","tag":["横轉光"]},
{"no":"4003","tag":["横轉光"]},
{"no":"4004","tag":["横轉木"]},
{"no":"4005","tag":["横轉木"]},
{"no":"4006","tag":["横轉光"]},
{"no":"4007","tag":["横轉木"]},
{"no":"4008","tag":["隨機轉回復"]},
{"no":"4009","tag":["隨機轉水"]},
{"no":"4010","tag":["隨機轉光"]},
{"no":"4011","tag":["隨機轉闇","隨機轉回復"]},
{"no":"4015","tag":["全轉火","全轉水","全轉木","全轉光","全轉暗","全轉回復"]},
{"no":"4016","tag":["全轉火","全轉水","全轉木","全轉光","全轉暗","全轉回復"]},
{"no":"4017","tag":["回復轉火"]},
{"no":"4018","tag":["全轉火","全轉水","全轉光","全轉回復"]},
{"no":"4019","tag":["回復轉光","邪魔轉光","毒轉光"]},
{"no":"4020","tag":["回復轉光","邪魔轉光","毒轉光"]},
{"no":"4021","tag":["全轉火","全轉水","全轉木","全轉光","全轉暗","全轉回復"]},
{"no":"4022","tag":["全轉火","全轉水","全轉木","全轉光","全轉暗","全轉回復"]},
{"no":"4023","tag":["木轉火","闇轉火"]},
{"no":"4024","tag":["木轉火","闇轉火"]},
{"no":"4030","tag":["邪魔轉光","毒轉光"]},
{"no":"4033","tag":["隨機轉光","隨機轉闇"]},
{"no":"4034","tag":["隨機轉光","隨機轉闇"]},
{"no":"4038","tag":["回復轉光","邪魔轉光","毒轉光"]},
{"no":"4039","tag":["全轉火","全轉水","全轉木","全轉光","全轉暗","全轉回復"]},
{"no":"4040","tag":["木轉火","闇轉火"]},
{"no":"4045","tag":["邪魔轉光","毒轉光"]},
{"no":"4051","tag":["光轉木","回復轉木","邪魔轉木","毒轉木"]},
{"no":"4052","tag":["光轉木","回復轉木","邪魔轉木","毒轉木"]},
{"no":"4053","tag":["木轉闇","回復轉闇","邪魔轉闇","毒轉闇"]},
{"no":"4054","tag":["木轉闇","回復轉闇","邪魔轉闇","毒轉闇"]},
{"no":"4055","tag":["全轉火","全轉水","全轉木","全轉光","全轉闇"]},
{"no":"4056","tag":["全轉火","全轉水","全轉木","全轉光","全轉暗","全轉回復"]},
{"no":"4063","tag":["隨機轉火","隨機轉回復"]},
{"no":"4064","tag":["全轉火","全轉光","全轉回復"]},
{"no":"4065","tag":["全轉火","全轉水","全轉木","全轉光","全轉回復"]},
{"no":"4066","tag":["水轉火","闇轉回復"]},
{"no":"4068","tag":["全轉火","全轉水","全轉木","全轉光","全轉回復"]},
{"no":"4069","tag":["水轉火","闇轉回復"]},
{"no":"4070","tag":["全轉火","全轉光","全轉回復"]},
{"no":"4071","tag":["隨機轉火","隨機轉回復"]},
{"no":"4072","tag":["隨機轉火","隨機轉回復"]},
{"no":"4073","tag":["火轉水","木轉水"]},
{"no":"4074","tag":["火轉水","木轉水"]},
{"no":"4076","tag":["全轉火","全轉回復"]},
{"no":"4077","tag":["全轉火","全轉回復"]},
{"no":"4078","tag":["全轉火","全轉回復"]},
{"no":"4079","tag":["縦轉火","縦轉光"]},
{"no":"4080","tag":["縦轉火","縦轉光"]},
{"no":"4081","tag":["縦轉火","縦轉光"]},
{"no":"4082","tag":["横轉光"]},
{"no":"4083","tag":["横轉光"]},
{"no":"4084","tag":["横轉光","横轉光"]},
{"no":"4087","tag":["全轉火","全轉木","全轉闇","全轉回復"]},
{"no":"4088","tag":["隨機轉火"]},
{"no":"4089","tag":["隨機轉火"]},
{"no":"4090","tag":["全轉火","全轉水","全轉光"]},
{"no":"4091","tag":["全轉火","全轉水","全轉木","全轉光","全轉闇"]},
{"no":"4092","tag":["全轉火","全轉水","全轉木","全轉光","全轉闇"]},
{"no":"4093","tag":["隨機轉闇"]},
{"no":"4096","tag":["全轉火","全轉水","全轉光","全轉回復"]},
{"no":"4097","tag":["全轉火","全轉水","全轉光","全轉回復"]},
{"no":"4102","tag":["光轉木","闇轉木","毒轉木"]},
{"no":"4103","tag":["光轉木","闇轉木","毒轉木"]},
{"no":"4110","tag":["全轉火","全轉水","全轉木"]},
{"no":"4111","tag":["全轉火","全轉水","全轉木"]},
{"no":"4112","tag":["隨機轉闇","隨機轉邪魔"]},
{"no":"4113","tag":["全轉火","全轉回復"]},
{"no":"4114","tag":["縦轉火","縦轉光"]},
{"no":"4115","tag":["横轉光"]},
{"no":"4117","tag":["隨機轉火"]},
{"no":"4118","tag":["全轉火","全轉水","全轉木","全轉光","全轉闇"]},
{"no":"4121","tag":["回復轉闇","毒轉闇"]},
{"no":"4122","tag":["回復轉闇","毒轉闇"]},
{"no":"4123","tag":["回復轉闇","毒轉闇"]},
{"no":"4124","tag":["回復轉闇","毒轉闇"]},
{"no":"4125","tag":["木轉火","回復轉木"]},
{"no":"4126","tag":["隨機轉闇","隨機轉邪魔"]},
{"no":"4128","tag":["横轉回復"]},
{"no":"4131","tag":["横轉回復"]},
{"no":"4133","tag":["全轉水","全轉光","全轉回復"]},
{"no":"4134","tag":["横轉邪魔","横轉邪魔"]},
{"no":"4135","tag":["全轉火","全轉水","全轉木","全轉光","全轉闇"]},
{"no":"4136","tag":["全轉水","全轉闇","全轉回復"]},
{"no":"4138","tag":["縦轉闇","縦轉回復"]},
{"no":"4139","tag":["隨機轉火"]},
{"no":"4141","tag":["横轉光"]},
{"no":"4142","tag":["全轉火","全轉木","全轉邪魔"]},
{"no":"4143","tag":["縦轉闇"]},
{"no":"4144","tag":["闇轉水","木轉回復"]},
{"no":"4145","tag":["縦轉火"]},
{"no":"4146","tag":["隨機轉水","隨機轉木","隨機轉闇"]},
{"no":"4149","tag":["全轉火","全轉水","全轉木","全轉光","全轉闇"]},
{"no":"4151","tag":["全轉水","全轉光","全轉回復"]},
{"no":"4152","tag":["横轉邪魔","横轉邪魔"]},
{"no":"4153","tag":["全轉火","全轉水","全轉木","全轉光","全轉闇"]},
{"no":"4154","tag":["全轉水","全轉闇","全轉回復"]},
{"no":"4156","tag":["縦轉闇","縦轉回復"]},
{"no":"4159","tag":["全轉水","全轉光","全轉回復"]},
{"no":"4162","tag":["横轉邪魔","横轉邪魔"]},
{"no":"4163","tag":["全轉火","全轉水","全轉木","全轉光","全轉闇"]},
{"no":"4164","tag":["全轉水","全轉闇","全轉回復"]},
{"no":"4168","tag":["全轉火","全轉水","全轉木","全轉闇"]},
{"no":"4169","tag":["全轉火","全轉水","全轉木","全轉闇"]},
{"no":"4170","tag":["縦轉闇","縦轉回復"]},
{"no":"4172","tag":["全轉火","全轉水","全轉木","全轉闇"]},
{"no":"4176","tag":["木轉火","邪魔轉火","毒轉火"]},
{"no":"4177","tag":["木轉火","邪魔轉火","毒轉火"]},
{"no":"4178","tag":["火轉水","邪魔轉水","毒轉水"]},
{"no":"4179","tag":["火轉水","邪魔轉水","毒轉水"]},
{"no":"4180","tag":["水轉木","邪魔轉木","毒轉木"]},
{"no":"4181","tag":["水轉木","邪魔轉木","毒轉木"]},
{"no":"4186","tag":["全轉闇","全轉回復"]},
{"no":"4187","tag":["全轉闇","全轉回復"]},
{"no":"4190","tag":["水轉光","闇轉回復"]},
{"no":"4191","tag":["水轉光","闇轉回復"]},
{"no":"4192","tag":["全轉闇","全轉回復"]},
{"no":"4194","tag":["水轉光","闇轉回復"]},
{"no":"4195","tag":["全轉火","全轉闇","全轉回復"]},
{"no":"4196","tag":["全轉火","全轉闇","全轉回復"]},
{"no":"4197","tag":["全轉木","全轉光","全轉闇","全轉回復"]},
{"no":"4198","tag":["全轉木","全轉光","全轉闇","全轉回復"]},
{"no":"4199","tag":["火轉木","光轉木"]},
{"no":"4200","tag":["火轉木","光轉木"]},
{"no":"4201","tag":["全轉火","全轉闇","全轉回復"]},
{"no":"4202","tag":["全轉木","全轉光","全轉闇","全轉回復"]},
{"no":"4203","tag":["火轉木","光轉木"]},
{"no":"4204","tag":["全轉光","全轉闇","全轉回復"]},
{"no":"4205","tag":["火轉木","邪魔轉木","毒轉木"]},
{"no":"4210","tag":["全轉火","全轉木","全轉光"]},
{"no":"4211","tag":["全轉水","全轉木","全轉闇"]},
{"no":"4212","tag":["全轉木","全轉光","全轉闇"]},
{"no":"4213","tag":["全轉火","全轉水","全轉木","全轉光"]},
{"no":"4214","tag":["全轉火","全轉水","全轉木","全轉光"]},
{"no":"4215","tag":["全轉火","全轉水","全轉闇"]},
{"no":"4217","tag":["火轉木","邪魔轉木","毒轉木"]},
{"no":"4219","tag":["全轉光","全轉闇","全轉回復"]},
{"no":"4220","tag":["全轉火","全轉木","全轉光"]},
{"no":"4221","tag":["全轉水","全轉木","全轉闇"]},
{"no":"4222","tag":["全轉木","全轉光","全轉闇"]},
{"no":"4223","tag":["全轉火","全轉水","全轉木","全轉光"]},
{"no":"4224","tag":["全轉火","全轉水","全轉闇"]},
{"no":"4226","tag":["縦轉回復"]},
{"no":"4227","tag":["全轉火","全轉水","全轉木","全轉光","全轉闇"]},
{"no":"4228","tag":["全轉火","全轉水","全轉木","全轉光","全轉闇"]},
{"no":"4229","tag":["全轉火","全轉水","全轉木","全轉光","全轉闇"]},
{"no":"4230","tag":["全轉火","全轉水","全轉木","全轉光","全轉闇"]},
{"no":"4231","tag":["全轉火","全轉水","全轉木","全轉光","全轉闇"]},
{"no":"4237","tag":["水轉光","闇轉回復"]},
{"no":"4238","tag":["火轉光","闇轉回復"]},
{"no":"4239","tag":["水轉光","火轉回復"]},
{"no":"4240","tag":["水轉闇","木轉回復"]},
{"no":"4241","tag":["火轉木","光轉回復"]},
{"no":"4242","tag":["回復轉火","邪魔轉火","毒轉火"]},
{"no":"4243","tag":["回復轉水","邪魔轉水","毒轉水"]},
{"no":"4244","tag":["回復轉木","邪魔轉木","毒轉木"]},
{"no":"4245","tag":["回復轉光","邪魔轉光","毒轉光"]},
{"no":"4246","tag":["回復轉闇","邪魔轉闇","毒轉闇"]},
{"no":"4248","tag":["全轉火","全轉光","全轉闇"]},
{"no":"4249","tag":["火轉水","回復轉水"]},
{"no":"4250","tag":["火轉水","回復轉水","邪魔轉回復","毒轉回復"]},
{"no":"4252","tag":["横轉木"]},
{"no":"4254","tag":["隨機轉光"]},
{"no":"4256","tag":["隨機轉闇"]},
{"no":"4261","tag":["光轉火","闇轉回復"]},
{"no":"4262","tag":["光轉水","闇轉回復"]},
{"no":"4263","tag":["光轉木","闇轉回復"]},
{"no":"4265","tag":["縦轉闇","縦轉回復"]},
{"no":"4266","tag":["木轉火","邪魔轉火","毒轉火"]},
{"no":"4267","tag":["火轉水","邪魔轉水","毒轉水"]},
{"no":"4268","tag":["水轉光","邪魔轉光","毒轉光"]},
{"no":"4269","tag":["縦轉火"]},
{"no":"4270","tag":["縦轉水"]},
{"no":"4271","tag":["縦轉木"]},
{"no":"4274","tag":["木轉火","闇轉回復","邪魔轉水","毒轉水"]},
{"no":"4275","tag":["火轉水","光轉回復","邪魔轉木","毒轉木"]},
{"no":"4276","tag":["水轉木","火轉回復","邪魔轉闇","毒轉闇"]},
{"no":"4277","tag":["水轉光","闇轉回復"]},
{"no":"4278","tag":["回復轉火","邪魔轉火","毒轉火"]},
{"no":"4279","tag":["縦轉水"]},
{"no":"4280","tag":["縦轉木"]},
{"no":"4281","tag":["回復轉光","邪魔轉光","毒轉光"]},
{"no":"4282","tag":["横轉闇"]},
{"no":"4283","tag":["全轉水","全轉闇"]},
{"no":"4284","tag":["全轉木","全轉闇"]},
{"no":"4285","tag":["全轉闇"]},
{"no":"4286","tag":["全轉闇"]},
{"no":"4287","tag":["縦轉木","縦轉闇"]},
{"no":"4289","tag":["全轉火","全轉木","全轉光","全轉闇","全轉回復"]},
{"no":"4291","tag":["回復轉光","邪魔轉光","毒轉光"]},
{"no":"4292","tag":["回復轉光","毒轉光"]},
{"no":"4294","tag":["全轉水","全轉木","全轉光"]},
{"no":"4295","tag":["隨機轉火","隨機轉水"]},
{"no":"4297","tag":["全轉火","全轉水","全轉木","全轉光","全轉暗","全轉回復"]},
{"no":"4298","tag":["全轉火","全轉水","全轉木","全轉光"]},
{"no":"4301","tag":["全轉水","全轉光"]},
{"no":"4302","tag":["全轉水","全轉光"]},
{"no":"4304","tag":["火轉木","邪魔轉木","毒轉木"]},
{"no":"4305","tag":["隨機轉闇"]},
{"no":"4306","tag":["隨機轉闇"]},
{"no":"4307","tag":["縦轉回復"]},
{"no":"4308","tag":["縦轉回復"]},
{"no":"4309","tag":["隨機轉闇"]},
{"no":"4310","tag":["隨機轉闇"]},
{"no":"4311","tag":["縦轉光"]},
{"no":"4312","tag":["縦轉水","縦轉光"]},
{"no":"4317","tag":["横轉木","横轉木"]},
{"no":"4318","tag":["全轉火","全轉闇","全轉邪魔"]},
{"no":"4325","tag":["全轉水","全轉光"]},
{"no":"4326","tag":["火轉木","邪魔轉木","毒轉木"]},
{"no":"4327","tag":["隨機轉闇"]},
{"no":"4328","tag":["縦轉回復"]},
{"no":"4329","tag":["隨機轉闇"]},
{"no":"4330","tag":["縦轉光"]},
{"no":"4331","tag":["縦轉水","縦轉光"]},
{"no":"4336","tag":["横轉木","横轉木"]},
{"no":"4337","tag":["全轉火","全轉闇","全轉邪魔"]},
{"no":"4344","tag":["全轉火","全轉水","全轉木","全轉光","全轉暗","全轉回復"]},
{"no":"4345","tag":["全轉火","全轉木","全轉光","全轉回復"]},
{"no":"4347","tag":["全轉水","全轉木","全轉光"]},
{"no":"4348","tag":["全轉火","全轉水","全轉木","全轉闇"]},
{"no":"4349","tag":["全轉水","全轉木","全轉光"]},
{"no":"4350","tag":["全轉火","全轉水","全轉木","全轉光","全轉暗","全轉回復"]},
{"no":"4354","tag":["隨機轉木"]},
{"no":"4359","tag":["縦轉火"]},
{"no":"4360","tag":["縦轉火"]},
{"no":"4363","tag":["隨機轉木"]},
{"no":"4364","tag":["隨機轉木"]},
{"no":"4367","tag":["全轉火","全轉水","全轉闇"]},
{"no":"4368","tag":["全轉火","全轉水","全轉闇"]},
{"no":"4374","tag":["全轉火","全轉水","全轉木","全轉光","全轉暗","全轉回復"]},
{"no":"4375","tag":["全轉火","全轉水","全轉木","全轉光","全轉暗","全轉回復"]},
{"no":"4376","tag":["隨機轉光"]},
{"no":"4377","tag":["隨機轉光"]},
{"no":"4383","tag":["隨機轉光"]},
{"no":"4386","tag":["光轉火","邪魔轉火","闇轉水","毒轉水"]},
{"no":"4387","tag":["水轉光"]},
{"no":"4388","tag":["隨機轉木"]},
{"no":"4389","tag":["全轉火","全轉水","全轉木","全轉光","全轉暗","全轉回復","全轉邪魔","全轉毒","全轉猛毒"]},
{"no":"4390","tag":["全轉火","全轉水","全轉木","全轉光","全轉暗","全轉回復","全轉邪魔","全轉毒","全轉猛毒"]},
{"no":"4393","tag":["邪魔轉水","毒轉水"]},
{"no":"4394","tag":["邪魔轉水","毒轉水"]},
{"no":"4400","tag":["全轉火","全轉水","全轉木","全轉光","全轉暗","全轉回復"]},
{"no":"4401","tag":["隨機轉光"]},
{"no":"4405","tag":["隨機轉光"]},
{"no":"4408","tag":["光轉火","邪魔轉火","闇轉水","毒轉水"]},
{"no":"4409","tag":["水轉光"]},
{"no":"4412","tag":["全轉火","全轉水","全轉木","全轉光","全轉暗","全轉回復"]},
{"no":"4413","tag":["全轉火","全轉水","全轉木","全轉光","全轉暗","全轉回復"]},
{"no":"4414","tag":["全轉木","全轉回復"]},
{"no":"4415","tag":["全轉木","全轉回復"]},
{"no":"4418","tag":["隨機轉回復"]},
{"no":"4419","tag":["隨機轉回復"]},
{"no":"4422","tag":["横轉火","横轉闇"]},
{"no":"4423","tag":["横轉火","横轉闇"]},
{"no":"4424","tag":["横轉火","横轉闇"]},
{"no":"4428","tag":["隨機轉回復"]},
{"no":"4429","tag":["隨機轉火","隨機轉回復"]},
{"no":"4430","tag":["光轉水","回復轉水"]},
{"no":"4431","tag":["光轉火","回復轉火"]},
{"no":"4432","tag":["闇轉火","邪魔轉火","毒轉火"]},
{"no":"4433","tag":["闇轉火","邪魔轉火","毒轉火"]},
{"no":"4435","tag":["縦轉火"]},
{"no":"4438","tag":["横轉木"]},
{"no":"4439","tag":["横轉光"]},
{"no":"4440","tag":["横轉光"]},
{"no":"4442","tag":["縦轉光","縦轉邪魔"]},
{"no":"4443","tag":["縦轉光","縦轉邪魔"]},
{"no":"4445","tag":["闇轉火","邪魔轉火","毒轉火"]},
{"no":"4447","tag":["横轉光"]},
{"no":"4448","tag":["全轉火","全轉木","全轉回復"]},
{"no":"4449","tag":["全轉水","全轉光","全轉回復"]},
{"no":"4450","tag":["全轉木","全轉闇","全轉回復"]},
{"no":"4451","tag":["全轉火","全轉水","全轉木","全轉光","全轉回復"]},
{"no":"4452","tag":["全轉火","全轉水","全轉木","全轉闇","全轉回復"]},
{"no":"4470","tag":["全轉火"]},
{"no":"4473","tag":["全轉火","全轉水","全轉木","全轉光","全轉暗","全轉回復","全轉邪魔"]},
{"no":"4474","tag":["光轉火","闇轉邪魔"]},
{"no":"4476","tag":["隨機轉火"]},
{"no":"4477","tag":["木轉回復"]},
{"no":"4478","tag":["水轉火"]},
{"no":"4479","tag":["水轉邪魔","毒轉邪魔"]},
{"no":"4480","tag":["毒轉邪魔"]},
{"no":"4481","tag":["隨機轉邪魔"]},
{"no":"4482","tag":["闇轉火"]},
{"no":"4483","tag":["回復轉火"]},
{"no":"4488","tag":["全轉水"]},
{"no":"4490","tag":["全轉水"]},
{"no":"4491","tag":["隨機轉水","隨機轉回復"]},
{"no":"4492","tag":["全轉火","全轉水","全轉木","全轉光","全轉闇"]},
{"no":"4493","tag":["全轉水"]},
{"no":"4495","tag":["火轉回復"]},
{"no":"4496","tag":["木轉水"]},
{"no":"4501","tag":["光轉水","回復轉木"]},
{"no":"4502","tag":["光轉水"]},
{"no":"4503","tag":["回復轉水"]},
{"no":"4506","tag":["全轉木"]},
{"no":"4510","tag":["水轉回復","光轉猛毒"]},
{"no":"4511","tag":["全轉火","全轉水","全轉木","全轉光","全轉暗","全轉回復","全轉毒"]},
{"no":"4512","tag":["全轉火","全轉水","全轉木","全轉光","全轉暗","全轉回復"]},
{"no":"4513","tag":["水轉回復"]},
{"no":"4514","tag":["火轉木"]},
{"no":"4516","tag":["光轉木"]},
{"no":"4517","tag":["隨機轉木"]},
{"no":"4520","tag":["全轉火","全轉水","全轉木","全轉光","全轉暗","全轉邪魔"]},
{"no":"4521","tag":["隨機轉木","隨機轉邪魔"]},
{"no":"4523","tag":["闇轉木"]},
{"no":"4524","tag":["回復轉木"]},
{"no":"4525","tag":["隨機轉木"]},
{"no":"4533","tag":["隨機轉水","隨機轉光"]},
{"no":"4536","tag":["隨機轉光"]},
{"no":"4538","tag":["隨機轉光"]},
{"no":"4539","tag":["闇轉回復"]},
{"no":"4540","tag":["闇轉光"]},
{"no":"4541","tag":["邪魔轉回復","毒轉回復"]},
{"no":"4545","tag":["闇轉光"]},
{"no":"4547","tag":["水轉光"]},
{"no":"4548","tag":["回復轉光"]},
{"no":"4551","tag":["隨機轉回復"]},
{"no":"4558","tag":["隨機轉闇","隨機轉回復"]},
{"no":"4559","tag":["木轉回復"]},
{"no":"4561","tag":["隨機轉闇"]},
{"no":"4562","tag":["光轉回復"]},
{"no":"4563","tag":["光轉闇"]},
{"no":"4572","tag":["回復轉闇"]},
{"no":"4573","tag":["回復轉闇"]},
{"no":"4577","tag":["全轉木","全轉光","全轉闇"]},
{"no":"4578","tag":["全轉火","全轉水","全轉木","全轉光"]},
{"no":"4580","tag":["全轉火","全轉木","全轉闇"]},
{"no":"4581","tag":["全轉火","全轉水","全轉光"]},
{"no":"4582","tag":["全轉水","全轉木","全轉光"]},
{"no":"4584","tag":["全轉水","全轉木","全轉闇"]},
{"no":"4585","tag":["全轉光","全轉回復"]},
{"no":"4586","tag":["全轉光","全轉回復"]},
{"no":"4587","tag":["縦轉光","縦轉回復"]},
{"no":"4588","tag":["全轉火","全轉水","全轉木","全轉光","全轉暗","全轉回復"]},
{"no":"4589","tag":["横轉木"]},
{"no":"4590","tag":["全轉火","全轉水","全轉木","全轉光","全轉暗","全轉回復"]},
{"no":"4591","tag":["横轉木"]},
{"no":"4592","tag":["全轉水","全轉木","全轉光","全轉回復"]},
{"no":"4593","tag":["縦轉回復","縦轉水"]},
{"no":"4594","tag":["光轉闇","爆弾轉闇"]},
{"no":"4595","tag":["全轉水","全轉木","全轉光","全轉回復"]},
{"no":"4596","tag":["縦轉回復","縦轉水"]},
{"no":"4597","tag":["光轉闇","爆弾轉闇"]},
{"no":"4598","tag":["全轉光","全轉回復","全轉邪魔"]},
{"no":"4599","tag":["全轉光","全轉回復","全轉邪魔"]},
{"no":"4604","tag":["全轉木","全轉闇","全轉回復"]},
{"no":"4605","tag":["全轉木","全轉闇","全轉回復"]},
{"no":"4607","tag":["木轉光","邪魔轉光","毒轉光"]},
{"no":"4610","tag":["横轉闇"]},
{"no":"4611","tag":["縦轉火"]},
{"no":"4613","tag":["隨機轉闇","隨機轉毒"]},
{"no":"4614","tag":["隨機轉闇","隨機轉毒"]},
{"no":"4619","tag":["全轉光","全轉回復","全轉邪魔"]},
{"no":"4622","tag":["全轉木","全轉闇","全轉回復"]},
{"no":"4624","tag":["木轉光","邪魔轉光","毒轉光"]},
{"no":"4627","tag":["横轉闇"]},
{"no":"4628","tag":["縦轉火"]},
{"no":"4630","tag":["全轉光","全轉回復","全轉邪魔"]},
{"no":"4633","tag":["全轉木","全轉闇","全轉回復"]},
{"no":"4634","tag":["横轉回復"]},
{"no":"4635","tag":["横轉回復"]},
{"no":"4636","tag":["全轉火","全轉水","全轉木","全轉光","全轉暗","全轉回復"]},
{"no":"4637","tag":["全轉火","全轉木","全轉光","全轉回復"]},
{"no":"4638","tag":["全轉火","全轉木","全轉光","全轉回復"]},
{"no":"4639","tag":["全轉水","全轉木","全轉闇","全轉回復"]},
{"no":"4640","tag":["全轉水","全轉木","全轉闇","全轉回復"]},
{"no":"4641","tag":["全轉木","全轉光","全轉闇","全轉回復"]},
{"no":"4642","tag":["全轉木","全轉光","全轉闇","全轉回復"]},
{"no":"4643","tag":["全轉火","全轉水","全轉光","全轉回復"]},
{"no":"4644","tag":["全轉火","全轉水","全轉光","全轉回復"]},
{"no":"4645","tag":["全轉火","全轉水","全轉闇","全轉回復"]},
{"no":"4646","tag":["全轉火","全轉水","全轉闇","全轉回復"]},
{"no":"4647","tag":["全轉光"]},
{"no":"4648","tag":["全轉光"]},
{"no":"4649","tag":["火轉闇","光轉闇"]},
{"no":"4650","tag":["火轉闇","光轉闇"]},
{"no":"4651","tag":["横轉火","横轉邪魔"]},
{"no":"4652","tag":["横轉火","横轉邪魔"]},
{"no":"4655","tag":["横轉火"]},
{"no":"4656","tag":["横轉火"]},
{"no":"4657","tag":["全轉火","全轉水"]},
{"no":"4658","tag":["全轉火","全轉水"]},
{"no":"4659","tag":["全轉木","全轉光","全轉回復"]},
{"no":"4660","tag":["全轉木","全轉光","全轉回復"]},
{"no":"4661","tag":["全轉火","全轉闇"]},
{"no":"4662","tag":["全轉火","全轉闇"]},
{"no":"4663","tag":["全轉火","全轉水","全轉闇"]},
{"no":"4664","tag":["全轉火","全轉水","全轉闇"]},
{"no":"4665","tag":["縦轉木"]},
{"no":"4667","tag":["縦轉闇"]},
{"no":"4669","tag":["隨機轉回復"]},
{"no":"4670","tag":["隨機轉水"]},
{"no":"4672","tag":["闇轉木","邪魔轉木","火轉水","毒轉水"]},
{"no":"4673","tag":["全轉水","全轉光","全轉闇"]},
{"no":"4674","tag":["全轉水","全轉光","全轉闇"]},
{"no":"4676","tag":["縦轉回復"]},
{"no":"4677","tag":["縦轉回復"]},
{"no":"4678","tag":["隨機轉火"]},
{"no":"4685","tag":["回復轉水","邪魔轉水","毒轉水"]},
{"no":"4686","tag":["回復轉水","邪魔轉水","毒轉水"]},
{"no":"4687","tag":["縦轉闇","縦轉木"]},
{"no":"4689","tag":["隨機轉闇"]},
{"no":"4690","tag":["全轉火","横轉火"]},
{"no":"4691","tag":["横轉水","縦轉水"]},
{"no":"4692","tag":["全轉火","全轉闇","全轉回復"]},
{"no":"4694","tag":["横轉水"]},
{"no":"4695","tag":["横轉光","毒轉回復","邪魔轉回復"]},
{"no":"4698","tag":["水轉闇"]},
{"no":"4699","tag":["回復轉光","邪魔轉光","毒轉光"]},
{"no":"4700","tag":["回復轉光","邪魔轉光","毒轉光"]},
{"no":"4701","tag":["光轉水","毒轉水"]},
{"no":"4702","tag":["光轉水","毒轉水"]},
{"no":"4703","tag":["全轉火","全轉光"]},
{"no":"4704","tag":["全轉火","全轉光"]},
{"no":"4705","tag":["火轉木","闇轉木","邪魔轉木","毒轉木"]},
{"no":"4706","tag":["火轉木","闇轉木","邪魔轉木","毒轉木"]},
{"no":"4709","tag":["隨機轉水"]},
{"no":"4710","tag":["全轉水","全轉木","全轉光","全轉回復"]},
{"no":"4719","tag":["縦轉回復"]},
{"no":"4721","tag":["横轉火"]},
{"no":"4724","tag":["回復轉光","邪魔轉光","毒轉光"]},
{"no":"4725","tag":["光轉水","毒轉水"]},
{"no":"4726","tag":["全轉火","全轉光"]},
{"no":"4727","tag":["火轉木","闇轉木","邪魔轉木","毒轉木"]},
{"no":"4728","tag":["横轉水","縦轉水"]},
{"no":"4729","tag":["隨機轉闇"]},
{"no":"4730","tag":["全轉火","横轉火"]},
{"no":"4731","tag":["隨機轉回復"]},
{"no":"4732","tag":["全轉水","全轉木","全轉回復"]},
{"no":"4733","tag":["全轉水","全轉木","全轉回復"]},
{"no":"4736","tag":["全轉水","全轉光","全轉回復"]},
{"no":"4737","tag":["全轉水","全轉光","全轉回復"]},
{"no":"4740","tag":["全轉光","全轉闇"]},
{"no":"4743","tag":["隨機轉木","隨機轉光"]},
{"no":"4744","tag":["隨機轉木","隨機轉光"]},
{"no":"4745","tag":["光轉火","邪魔轉火","木轉闇","毒轉闇"]},
{"no":"4746","tag":["全轉火","全轉水","全轉木","全轉光","全轉暗","全轉回復"]},
{"no":"4747","tag":["縦轉闇","縦轉回復"]},
{"no":"4749","tag":["全轉水","全轉光"]},
{"no":"4751","tag":["全轉木","全轉闇"]},
{"no":"4752","tag":["全轉木","全轉闇"]},
{"no":"4753","tag":["全轉木","全轉闇"]},
{"no":"4757","tag":["全轉火","全轉水","全轉木","全轉光","全轉暗"]},
{"no":"4758","tag":["全轉火","全轉水","全轉木","全轉光","全轉暗"]},
{"no":"4759","tag":["全轉火","全轉水","全轉木","全轉光","全轉暗"]},
{"no":"4763","tag":["横轉木","横轉光"]},
{"no":"4764","tag":["横轉木","横轉光"]},
{"no":"4765","tag":["闇轉火","毒轉火"]},
{"no":"4766","tag":["闇轉火","毒轉火"]},
{"no":"4767","tag":["全轉木","全轉光","全轉邪魔"]},
{"no":"4768","tag":["全轉木","全轉光","全轉邪魔"]},
{"no":"4769","tag":["隨機轉光"]},
{"no":"4770","tag":["隨機轉光"]},
{"no":"4771","tag":["縦轉爆弾","縦轉水"]},
{"no":"4772","tag":["縦轉爆弾","縦轉水"]},
{"no":"4779","tag":["隨機轉爆弾"]},
{"no":"4780","tag":["全轉火","全轉水","全轉木","全轉光","全轉闇"]},
{"no":"4781","tag":["全轉火","全轉光","全轉回復"]},
{"no":"4787","tag":["全轉水","全轉回復"]},
{"no":"4788","tag":["全轉火","全轉水"]},
{"no":"4789","tag":["全轉火","全轉水"]},
{"no":"4790","tag":["全轉水","全轉回復"]},
{"no":"4793","tag":["全轉水"]},
{"no":"4794","tag":["全轉水"]},
{"no":"4795","tag":["全轉水","全轉木","全轉光"]},
{"no":"4796","tag":["全轉火","全轉水","全轉回復"]},
{"no":"4797","tag":["全轉火","全轉水","全轉回復"]},
{"no":"4798","tag":["火轉木","邪魔轉木","水轉闇","毒轉闇"]},
{"no":"4799","tag":["火轉木","邪魔轉木","水轉闇","毒轉闇"]},
{"no":"4802","tag":["全轉火","全轉木","全轉回復"]},
{"no":"4803","tag":["全轉火","全轉木","全轉回復"]},
{"no":"4806","tag":["火轉闇","邪魔轉闇","毒轉闇"]},
{"no":"4807","tag":["火轉闇","邪魔轉闇","毒轉闇"]},
{"no":"4808","tag":["回復轉水","毒轉水"]},
{"no":"4809","tag":["回復轉水","毒轉水"]},
{"no":"4810","tag":["横轉闇"]},
{"no":"4811","tag":["横轉闇"]},
{"no":"4812","tag":["全轉水","全轉闇"]},
{"no":"4813","tag":["全轉木","全轉光"]},
{"no":"4814","tag":["全轉火","全轉光","全轉回復"]},
{"no":"4816","tag":["全轉木","全轉光","全轉闇"]},
{"no":"4817","tag":["火轉光","木轉光"]},
{"no":"4818","tag":["火轉光","木轉光"]},
{"no":"4819","tag":["横轉火"]},
{"no":"4820","tag":["横轉火"]},
{"no":"4821","tag":["木轉光","邪魔轉光","火轉闇","毒轉闇"]},
{"no":"4822","tag":["木轉光","邪魔轉光","火轉闇","毒轉闇"]},
{"no":"4823","tag":["火轉光","木轉光"]},
{"no":"4824","tag":["横轉火"]},
{"no":"4825","tag":["木轉光","邪魔轉光","火轉闇","毒轉闇"]},
{"no":"4826","tag":["隨機轉回復"]},
{"no":"4827","tag":["邪魔轉闇","毒轉闇","爆弾轉闇"]},
{"no":"4829","tag":["全轉木","全轉闇","全轉回復"]},
{"no":"4830","tag":["全轉光","全轉闇","全轉回復"]},
{"no":"4831","tag":["横轉闇","横轉木"]},
{"no":"4834","tag":["回復轉光","邪魔轉光","毒轉光"]},
{"no":"4835","tag":["回復轉光","邪魔轉光","毒轉光"]},
{"no":"4836","tag":["全轉光"]},
{"no":"4837","tag":["全轉光"]},
{"no":"4838","tag":["闇轉光","水轉回復"]},
{"no":"4839","tag":["闇轉光","水轉回復"]},
{"no":"4840","tag":["回復轉光","邪魔轉光","毒轉光"]},
{"no":"4841","tag":["全轉火","全轉水","全轉木","全轉光","全轉暗","全轉回復"]},
{"no":"4842","tag":["木轉火","闇轉火"]},
{"no":"4855","tag":["全轉水","全轉闇"]},
{"no":"4856","tag":["全轉水","全轉闇"]},
{"no":"4857","tag":["全轉水","全轉闇"]},
{"no":"4861","tag":["火轉木","邪魔轉木","毒轉木"]},
{"no":"4862","tag":["火轉木","邪魔轉木","毒轉木"]},
{"no":"4863","tag":["火轉木","邪魔轉木","毒轉木"]},
{"no":"4864","tag":["全轉火","全轉水","全轉木","全轉光","全轉暗"]},
{"no":"4865","tag":["全轉火","全轉水","全轉木","全轉光","全轉暗"]},
{"no":"4866","tag":["全轉火","全轉水","全轉木","全轉光","全轉暗"]},
{"no":"4867","tag":["縦轉火"]},
{"no":"4868","tag":["縦轉火"]},
{"no":"4869","tag":["縦轉火"]},
{"no":"4870","tag":["横轉火"]},
{"no":"4871","tag":["邪魔轉回復","毒轉回復"]},
{"no":"4872","tag":["隨機轉火"]},
{"no":"4873","tag":["縦轉水","縦轉回復"]},
{"no":"4874","tag":["隨機轉闇"]},
{"no":"4876","tag":["水轉光","毒轉光"]},
{"no":"4877","tag":["横轉水","横轉水"]},
{"no":"4878","tag":["全轉火","全轉水","全轉光","全轉闇"]},
{"no":"4882","tag":["横轉闇","横轉邪魔"]},
{"no":"4883","tag":["隨機轉木","隨機轉光"]},
{"no":"4884","tag":["隨機轉木","隨機轉光"]},
{"no":"4895","tag":["全轉水","全轉木","全轉光"]},
{"no":"4896","tag":["全轉水","全轉木","全轉光"]},
{"no":"4897","tag":["全轉水","全轉木","全轉光"]},
{"no":"4900","tag":["闇轉回復"]},
{"no":"4901","tag":["回復轉闇"]}]